{
	"start":	{
		"connected":	[{
				"socket":	5,
				"local_host":	"172.31.21.139",
				"local_port":	36856,
				"remote_host":	"34.222.140.92",
				"remote_port":	5201
			}],
		"version":	"iperf 3.16",
		"system_info":	"Linux ip-172-31-21-139 6.8.0-1018-aws #20-Ubuntu SMP Thu Oct 10 18:14:42 UTC 2024 x86_64",
		"timestamp":	{
			"time":	"Fri, 06 Dec 2024 22:42:50 GMT",
			"timesecs":	1733524970
		},
		"connecting_to":	{
			"host":	"34.222.140.92",
			"port":	5201
		},
		"cookie":	"g5wqf7a2uasaegkd4kfrwhgfysxthbh5jg54",
		"tcp_mss_default":	1448,
		"target_bitrate":	0,
		"fq_rate":	0,
		"sock_bufsize":	0,
		"sndbuf_actual":	16384,
		"rcvbuf_actual":	131072,
		"test_start":	{
			"protocol":	"TCP",
			"num_streams":	1,
			"blksize":	131072,
			"omit":	0,
			"duration":	30,
			"bytes":	0,
			"blocks":	0,
			"reverse":	0,
			"tos":	0,
			"target_bitrate":	0,
			"bidir":	0,
			"fqrate":	0
		}
	},
	"intervals":	[{
			"streams":	[{
					"socket":	5,
					"start":	0,
					"end":	0.200104,
					"seconds":	0.2001039981842041,
					"bytes":	655360,
					"bits_per_second":	26200775.8344424,
					"retransmits":	0,
					"snd_cwnd":	97016,
					"snd_wnd":	37888,
					"rtt":	22024,
					"rttvar":	69,
					"pmtu":	9001,
					"omitted":	false,
					"sender":	true
				}],
			"sum":	{
				"start":	0,
				"end":	0.200104,
				"seconds":	0.2001039981842041,
				"bytes":	655360,
				"bits_per_second":	26200775.8344424,
				"retransmits":	0,
				"omitted":	false,
				"sender":	true
			}
		}, {
			"streams":	[{
					"socket":	5,
					"start":	0.200104,
					"end":	0.400269,
					"seconds":	0.20016500353813171,
					"bytes":	393216,
					"bits_per_second":	15715674.290689552,
					"retransmits":	0,
					"snd_cwnd":	97016,
					"snd_wnd":	37888,
					"rtt":	21922,
					"rttvar":	94,
					"pmtu":	9001,
					"omitted":	false,
					"sender":	true
				}],
			"sum":	{
				"start":	0.200104,
				"end":	0.400269,
				"seconds":	0.20016500353813171,
				"bytes":	393216,
				"bits_per_second":	15715674.290689552,
				"retransmits":	0,
				"omitted":	false,
				"sender":	true
			}
		}, {
			"streams":	[{
					"socket":	5,
					"start":	0.400269,
					"end":	0.600275,
					"seconds":	0.20000599324703217,
					"bytes":	262144,
					"bits_per_second":	10485445.790665671,
					"retransmits":	0,
					"snd_cwnd":	97016,
					"snd_wnd":	37888,
					"rtt":	21846,
					"rttvar":	179,
					"pmtu":	9001,
					"omitted":	false,
					"sender":	true
				}],
			"sum":	{
				"start":	0.400269,
				"end":	0.600275,
				"seconds":	0.20000599324703217,
				"bytes":	262144,
				"bits_per_second":	10485445.790665671,
				"retransmits":	0,
				"omitted":	false,
				"sender":	true
			}
		}, {
			"streams":	[{
					"socket":	5,
					"start":	0.600275,
					"end":	0.800266,
					"seconds":	0.19999100267887115,
					"bytes":	4456448,
					"bits_per_second":	178265939.57952365,
					"retransmits":	342,
					"snd_cwnd":	525624,
					"snd_wnd":	1442048,
					"rtt":	22273,
					"rttvar":	253,
					"pmtu":	9001,
					"omitted":	false,
					"sender":	true
				}],
			"sum":	{
				"start":	0.600275,
				"end":	0.800266,
				"seconds":	0.19999100267887115,
				"bytes":	4456448,
				"bits_per_second":	178265939.57952365,
				"retransmits":	342,
				"omitted":	false,
				"sender":	true
			}
		}, {
			"streams":	[{
					"socket":	5,
					"start":	0.800266,
					"end":	1.000636,
					"seconds":	0.20036999881267548,
					"bytes":	3932160,
					"bits_per_second":	156995958.40896916,
					"retransmits":	27,
					"snd_cwnd":	343176,
					"snd_wnd":	1794176,
					"rtt":	21695,
					"rttvar":	253,
					"pmtu":	9001,
					"omitted":	false,
					"sender":	true
				}],
			"sum":	{
				"start":	0.800266,
				"end":	1.000636,
				"seconds":	0.20036999881267548,
				"bytes":	3932160,
				"bits_per_second":	156995958.40896916,
				"retransmits":	27,
				"omitted":	false,
				"sender":	true
			}
		}, {
			"streams":	[{
					"socket":	5,
					"start":	1.000636,
					"end":	1.20028,
					"seconds":	0.19964399933815,
					"bytes":	3145728,
					"bits_per_second":	126053495.63938062,
					"retransmits":	0,
					"snd_cwnd":	350416,
					"snd_wnd":	1815808,
					"rtt":	22146,
					"rttvar":	337,
					"pmtu":	9001,
					"omitted":	false,
					"sender":	true
				}],
			"sum":	{
				"start":	1.000636,
				"end":	1.20028,
				"seconds":	0.19964399933815,
				"bytes":	3145728,
				"bits_per_second":	126053495.63938062,
				"retransmits":	0,
				"omitted":	false,
				"sender":	true
			}
		}, {
			"streams":	[{
					"socket":	5,
					"start":	1.20028,
					"end":	1.400274,
					"seconds":	0.19999399781227112,
					"bytes":	3145728,
					"bits_per_second":	125832896.36333221,
					"retransmits":	0,
					"snd_cwnd":	357656,
					"snd_wnd":	1654144,
					"rtt":	22336,
					"rttvar":	515,
					"pmtu":	9001,
					"omitted":	false,
					"sender":	true
				}],
			"sum":	{
				"start":	1.20028,
				"end":	1.400274,
				"seconds":	0.19999399781227112,
				"bytes":	3145728,
				"bits_per_second":	125832896.36333221,
				"retransmits":	0,
				"omitted":	false,
				"sender":	true
			}
		}, {
			"streams":	[{
					"socket":	5,
					"start":	1.400274,
					"end":	1.600103,
					"seconds":	0.19982899725437164,
					"bytes":	4325376,
					"bits_per_second":	173163096.82499292,
					"retransmits":	0,
					"snd_cwnd":	364896,
					"snd_wnd":	1817216,
					"rtt":	22038,
					"rttvar":	88,
					"pmtu":	9001,
					"omitted":	false,
					"sender":	true
				}],
			"sum":	{
				"start":	1.400274,
				"end":	1.600103,
				"seconds":	0.19982899725437164,
				"bytes":	4325376,
				"bits_per_second":	173163096.82499292,
				"retransmits":	0,
				"omitted":	false,
				"sender":	true
			}
		}, {
			"streams":	[{
					"socket":	5,
					"start":	1.600103,
					"end":	1.800277,
					"seconds":	0.2001740038394928,
					"bytes":	2883584,
					"bits_per_second":	115243096.29384916,
					"retransmits":	0,
					"snd_cwnd":	372136,
					"snd_wnd":	1792768,
					"rtt":	22041,
					"rttvar":	150,
					"pmtu":	9001,
					"omitted":	false,
					"sender":	true
				}],
			"sum":	{
				"start":	1.600103,
				"end":	1.800277,
				"seconds":	0.2001740038394928,
				"bytes":	2883584,
				"bits_per_second":	115243096.29384916,
				"retransmits":	0,
				"omitted":	false,
				"sender":	true
			}
		}, {
			"streams":	[{
					"socket":	5,
					"start":	1.800277,
					"end":	2.000891,
					"seconds":	0.20061400532722473,
					"bytes":	3014656,
					"bits_per_second":	120217170.08571744,
					"retransmits":	0,
					"snd_cwnd":	376480,
					"snd_wnd":	1716224,
					"rtt":	21996,
					"rttvar":	317,
					"pmtu":	9001,
					"omitted":	false,
					"sender":	true
				}],
			"sum":	{
				"start":	1.800277,
				"end":	2.000891,
				"seconds":	0.20061400532722473,
				"bytes":	3014656,
				"bits_per_second":	120217170.08571744,
				"retransmits":	0,
				"omitted":	false,
				"sender":	true
			}
		}, {
			"streams":	[{
					"socket":	5,
					"start":	2.000891,
					"end":	2.200243,
					"seconds":	0.19935199618339539,
					"bytes":	4587520,
					"bits_per_second":	184097278.696108,
					"retransmits":	0,
					"snd_cwnd":	382272,
					"snd_wnd":	1817216,
					"rtt":	21596,
					"rttvar":	92,
					"pmtu":	9001,
					"omitted":	false,
					"sender":	true
				}],
			"sum":	{
				"start":	2.000891,
				"end":	2.200243,
				"seconds":	0.19935199618339539,
				"bytes":	4587520,
				"bits_per_second":	184097278.696108,
				"retransmits":	0,
				"omitted":	false,
				"sender":	true
			}
		}, {
			"streams":	[{
					"socket":	5,
					"start":	2.200243,
					"end":	2.400265,
					"seconds":	0.20002199709415436,
					"bytes":	3014656,
					"bits_per_second":	120572978.72417267,
					"retransmits":	0,
					"snd_cwnd":	389512,
					"snd_wnd":	1817216,
					"rtt":	21974,
					"rttvar":	837,
					"pmtu":	9001,
					"omitted":	false,
					"sender":	true
				}],
			"sum":	{
				"start":	2.200243,
				"end":	2.400265,
				"seconds":	0.20002199709415436,
				"bytes":	3014656,
				"bits_per_second":	120572978.72417267,
				"retransmits":	0,
				"omitted":	false,
				"sender":	true
			}
		}, {
			"streams":	[{
					"socket":	5,
					"start":	2.400265,
					"end":	2.600261,
					"seconds":	0.19999599456787109,
					"bytes":	3145728,
					"bits_per_second":	125831640.05046946,
					"retransmits":	0,
					"snd_cwnd":	396752,
					"snd_wnd":	1817216,
					"rtt":	23481,
					"rttvar":	2875,
					"pmtu":	9001,
					"omitted":	false,
					"sender":	true
				}],
			"sum":	{
				"start":	2.400265,
				"end":	2.600261,
				"seconds":	0.19999599456787109,
				"bytes":	3145728,
				"bits_per_second":	125831640.05046946,
				"retransmits":	0,
				"omitted":	false,
				"sender":	true
			}
		}, {
			"streams":	[{
					"socket":	5,
					"start":	2.600261,
					"end":	2.800438,
					"seconds":	0.20017699897289276,
					"bytes":	3276800,
					"bits_per_second":	130956104.52002959,
					"retransmits":	1,
					"snd_cwnd":	283808,
					"snd_wnd":	1817216,
					"rtt":	21748,
					"rttvar":	155,
					"pmtu":	9001,
					"omitted":	false,
					"sender":	true
				}],
			"sum":	{
				"start":	2.600261,
				"end":	2.800438,
				"seconds":	0.20017699897289276,
				"bytes":	3276800,
				"bits_per_second":	130956104.52002959,
				"retransmits":	1,
				"omitted":	false,
				"sender":	true
			}
		}, {
			"streams":	[{
					"socket":	5,
					"start":	2.800438,
					"end":	3.000268,
					"seconds":	0.19982999563217163,
					"bytes":	2883584,
					"bits_per_second":	115441487.78576092,
					"retransmits":	0,
					"snd_cwnd":	289600,
					"snd_wnd":	1812864,
					"rtt":	21655,
					"rttvar":	168,
					"pmtu":	9001,
					"omitted":	false,
					"sender":	true
				}],
			"sum":	{
				"start":	2.800438,
				"end":	3.000268,
				"seconds":	0.19982999563217163,
				"bytes":	2883584,
				"bits_per_second":	115441487.78576092,
				"retransmits":	0,
				"omitted":	false,
				"sender":	true
			}
		}, {
			"streams":	[{
					"socket":	5,
					"start":	3.000268,
					"end":	3.200249,
					"seconds":	0.19998100399971008,
					"bytes":	2883584,
					"bits_per_second":	115354316.35313444,
					"retransmits":	0,
					"snd_cwnd":	296840,
					"snd_wnd":	1818624,
					"rtt":	21787,
					"rttvar":	1030,
					"pmtu":	9001,
					"omitted":	false,
					"sender":	true
				}],
			"sum":	{
				"start":	3.000268,
				"end":	3.200249,
				"seconds":	0.19998100399971008,
				"bytes":	2883584,
				"bits_per_second":	115354316.35313444,
				"retransmits":	0,
				"omitted":	false,
				"sender":	true
			}
		}, {
			"streams":	[{
					"socket":	5,
					"start":	3.200249,
					"end":	3.402103,
					"seconds":	0.20185400545597076,
					"bytes":	2883584,
					"bits_per_second":	114283944.71484409,
					"retransmits":	0,
					"snd_cwnd":	302632,
					"snd_wnd":	1761024,
					"rtt":	21980,
					"rttvar":	55,
					"pmtu":	9001,
					"omitted":	false,
					"sender":	true
				}],
			"sum":	{
				"start":	3.200249,
				"end":	3.402103,
				"seconds":	0.20185400545597076,
				"bytes":	2883584,
				"bits_per_second":	114283944.71484409,
				"retransmits":	0,
				"omitted":	false,
				"sender":	true
			}
		}, {
			"streams":	[{
					"socket":	5,
					"start":	3.402103,
					"end":	3.600628,
					"seconds":	0.198524996638298,
					"bytes":	1572864,
					"bits_per_second":	63382003.339989446,
					"retransmits":	0,
					"snd_cwnd":	308424,
					"snd_wnd":	1766784,
					"rtt":	21812,
					"rttvar":	563,
					"pmtu":	9001,
					"omitted":	false,
					"sender":	true
				}],
			"sum":	{
				"start":	3.402103,
				"end":	3.600628,
				"seconds":	0.198524996638298,
				"bytes":	1572864,
				"bits_per_second":	63382003.339989446,
				"retransmits":	0,
				"omitted":	false,
				"sender":	true
			}
		}, {
			"streams":	[{
					"socket":	5,
					"start":	3.600628,
					"end":	3.800281,
					"seconds":	0.19965299963951111,
					"bytes":	2883584,
					"bits_per_second":	115543828.75114457,
					"retransmits":	0,
					"snd_cwnd":	315664,
					"snd_wnd":	1716224,
					"rtt":	21968,
					"rttvar":	27,
					"pmtu":	9001,
					"omitted":	false,
					"sender":	true
				}],
			"sum":	{
				"start":	3.600628,
				"end":	3.800281,
				"seconds":	0.19965299963951111,
				"bytes":	2883584,
				"bits_per_second":	115543828.75114457,
				"retransmits":	0,
				"omitted":	false,
				"sender":	true
			}
		}, {
			"streams":	[{
					"socket":	5,
					"start":	3.800281,
					"end":	4.000254,
					"seconds":	0.199973002076149,
					"bytes":	3145728,
					"bits_per_second":	125846107.91819261,
					"retransmits":	0,
					"snd_cwnd":	322904,
					"snd_wnd":	1818624,
					"rtt":	21603,
					"rttvar":	177,
					"pmtu":	9001,
					"omitted":	false,
					"sender":	true
				}],
			"sum":	{
				"start":	3.800281,
				"end":	4.000254,
				"seconds":	0.199973002076149,
				"bytes":	3145728,
				"bits_per_second":	125846107.91819261,
				"retransmits":	0,
				"omitted":	false,
				"sender":	true
			}
		}, {
			"streams":	[{
					"socket":	5,
					"start":	4.000254,
					"end":	4.200813,
					"seconds":	0.20055900514125824,
					"bytes":	3145728,
					"bits_per_second":	125478404.63346505,
					"retransmits":	0,
					"snd_cwnd":	330144,
					"snd_wnd":	1818624,
					"rtt":	21755,
					"rttvar":	197,
					"pmtu":	9001,
					"omitted":	false,
					"sender":	true
				}],
			"sum":	{
				"start":	4.000254,
				"end":	4.200813,
				"seconds":	0.20055900514125824,
				"bytes":	3145728,
				"bits_per_second":	125478404.63346505,
				"retransmits":	0,
				"omitted":	false,
				"sender":	true
			}
		}, {
			"streams":	[{
					"socket":	5,
					"start":	4.200813,
					"end":	4.400248,
					"seconds":	0.19943499565124512,
					"bytes":	3014656,
					"bits_per_second":	120927863.84478973,
					"retransmits":	0,
					"snd_cwnd":	335936,
					"snd_wnd":	1818624,
					"rtt":	21599,
					"rttvar":	496,
					"pmtu":	9001,
					"omitted":	false,
					"sender":	true
				}],
			"sum":	{
				"start":	4.200813,
				"end":	4.400248,
				"seconds":	0.19943499565124512,
				"bytes":	3014656,
				"bits_per_second":	120927863.84478973,
				"retransmits":	0,
				"omitted":	false,
				"sender":	true
			}
		}, {
			"streams":	[{
					"socket":	5,
					"start":	4.400248,
					"end":	4.600258,
					"seconds":	0.20001000165939331,
					"bytes":	3407872,
					"bits_per_second":	136308063.46588326,
					"retransmits":	0,
					"snd_cwnd":	344624,
					"snd_wnd":	1818624,
					"rtt":	22414,
					"rttvar":	983,
					"pmtu":	9001,
					"omitted":	false,
					"sender":	true
				}],
			"sum":	{
				"start":	4.400248,
				"end":	4.600258,
				"seconds":	0.20001000165939331,
				"bytes":	3407872,
				"bits_per_second":	136308063.46588326,
				"retransmits":	0,
				"omitted":	false,
				"sender":	true
			}
		}, {
			"streams":	[{
					"socket":	5,
					"start":	4.600258,
					"end":	4.800763,
					"seconds":	0.20050500333309174,
					"bytes":	3145728,
					"bits_per_second":	125512199.60428081,
					"retransmits":	0,
					"snd_cwnd":	350416,
					"snd_wnd":	1766784,
					"rtt":	22008,
					"rttvar":	292,
					"pmtu":	9001,
					"omitted":	false,
					"sender":	true
				}],
			"sum":	{
				"start":	4.600258,
				"end":	4.800763,
				"seconds":	0.20050500333309174,
				"bytes":	3145728,
				"bits_per_second":	125512199.60428081,
				"retransmits":	0,
				"omitted":	false,
				"sender":	true
			}
		}, {
			"streams":	[{
					"socket":	5,
					"start":	4.800763,
					"end":	5.000137,
					"seconds":	0.1993740051984787,
					"bytes":	2752512,
					"bits_per_second":	110446173.65277277,
					"retransmits":	0,
					"snd_cwnd":	359104,
					"snd_wnd":	1818624,
					"rtt":	21935,
					"rttvar":	324,
					"pmtu":	9001,
					"omitted":	false,
					"sender":	true
				}],
			"sum":	{
				"start":	4.800763,
				"end":	5.000137,
				"seconds":	0.1993740051984787,
				"bytes":	2752512,
				"bits_per_second":	110446173.65277277,
				"retransmits":	0,
				"omitted":	false,
				"sender":	true
			}
		}, {
			"streams":	[{
					"socket":	5,
					"start":	5.000137,
					"end":	5.2011,
					"seconds":	0.20096300542354584,
					"bytes":	3276800,
					"bits_per_second":	130443909.04062678,
					"retransmits":	6,
					"snd_cwnd":	257744,
					"snd_wnd":	1818624,
					"rtt":	21776,
					"rttvar":	281,
					"pmtu":	9001,
					"omitted":	false,
					"sender":	true
				}],
			"sum":	{
				"start":	5.000137,
				"end":	5.2011,
				"seconds":	0.20096300542354584,
				"bytes":	3276800,
				"bits_per_second":	130443909.04062678,
				"retransmits":	6,
				"omitted":	false,
				"sender":	true
			}
		}, {
			"streams":	[{
					"socket":	5,
					"start":	5.2011,
					"end":	5.400263,
					"seconds":	0.19916300475597382,
					"bytes":	1572864,
					"bits_per_second":	63178962.455488764,
					"retransmits":	0,
					"snd_cwnd":	270776,
					"snd_wnd":	1772544,
					"rtt":	21721,
					"rttvar":	225,
					"pmtu":	9001,
					"omitted":	false,
					"sender":	true
				}],
			"sum":	{
				"start":	5.2011,
				"end":	5.400263,
				"seconds":	0.19916300475597382,
				"bytes":	1572864,
				"bits_per_second":	63178962.455488764,
				"retransmits":	0,
				"omitted":	false,
				"sender":	true
			}
		}, {
			"streams":	[{
					"socket":	5,
					"start":	5.400263,
					"end":	5.600272,
					"seconds":	0.20000900328159332,
					"bytes":	2883584,
					"bits_per_second":	115338167.88998014,
					"retransmits":	0,
					"snd_cwnd":	278016,
					"snd_wnd":	1798528,
					"rtt":	21355,
					"rttvar":	713,
					"pmtu":	9001,
					"omitted":	false,
					"sender":	true
				}],
			"sum":	{
				"start":	5.400263,
				"end":	5.600272,
				"seconds":	0.20000900328159332,
				"bytes":	2883584,
				"bits_per_second":	115338167.88998014,
				"retransmits":	0,
				"omitted":	false,
				"sender":	true
			}
		}, {
			"streams":	[{
					"socket":	5,
					"start":	5.600272,
					"end":	5.80095,
					"seconds":	0.20067800581455231,
					"bytes":	2883584,
					"bits_per_second":	114953663.73790804,
					"retransmits":	0,
					"snd_cwnd":	288152,
					"snd_wnd":	1818624,
					"rtt":	21413,
					"rttvar":	292,
					"pmtu":	9001,
					"omitted":	false,
					"sender":	true
				}],
			"sum":	{
				"start":	5.600272,
				"end":	5.80095,
				"seconds":	0.20067800581455231,
				"bytes":	2883584,
				"bits_per_second":	114953663.73790804,
				"retransmits":	0,
				"omitted":	false,
				"sender":	true
			}
		}, {
			"streams":	[{
					"socket":	5,
					"start":	5.80095,
					"end":	6.000329,
					"seconds":	0.19937899708747864,
					"bytes":	2883584,
					"bits_per_second":	115702618.31479919,
					"retransmits":	0,
					"snd_cwnd":	296840,
					"snd_wnd":	1818624,
					"rtt":	22068,
					"rttvar":	741,
					"pmtu":	9001,
					"omitted":	false,
					"sender":	true
				}],
			"sum":	{
				"start":	5.80095,
				"end":	6.000329,
				"seconds":	0.19937899708747864,
				"bytes":	2883584,
				"bits_per_second":	115702618.31479919,
				"retransmits":	0,
				"omitted":	false,
				"sender":	true
			}
		}, {
			"streams":	[{
					"socket":	5,
					"start":	6.000329,
					"end":	6.200592,
					"seconds":	0.20026299357414246,
					"bytes":	1572864,
					"bits_per_second":	62831938.020248786,
					"retransmits":	0,
					"snd_cwnd":	304080,
					"snd_wnd":	1812864,
					"rtt":	21627,
					"rttvar":	345,
					"pmtu":	9001,
					"omitted":	false,
					"sender":	true
				}],
			"sum":	{
				"start":	6.000329,
				"end":	6.200592,
				"seconds":	0.20026299357414246,
				"bytes":	1572864,
				"bits_per_second":	62831938.020248786,
				"retransmits":	0,
				"omitted":	false,
				"sender":	true
			}
		}, {
			"streams":	[{
					"socket":	5,
					"start":	6.200592,
					"end":	6.400097,
					"seconds":	0.19950500130653381,
					"bytes":	3014656,
					"bits_per_second":	120885430.6511571,
					"retransmits":	0,
					"snd_cwnd":	311320,
					"snd_wnd":	1818624,
					"rtt":	21682,
					"rttvar":	118,
					"pmtu":	9001,
					"omitted":	false,
					"sender":	true
				}],
			"sum":	{
				"start":	6.200592,
				"end":	6.400097,
				"seconds":	0.19950500130653381,
				"bytes":	3014656,
				"bits_per_second":	120885430.6511571,
				"retransmits":	0,
				"omitted":	false,
				"sender":	true
			}
		}, {
			"streams":	[{
					"socket":	5,
					"start":	6.400097,
					"end":	6.600251,
					"seconds":	0.20015400648117065,
					"bytes":	3145728,
					"bits_per_second":	125732302.05295669,
					"retransmits":	0,
					"snd_cwnd":	318560,
					"snd_wnd":	1768192,
					"rtt":	21853,
					"rttvar":	217,
					"pmtu":	9001,
					"omitted":	false,
					"sender":	true
				}],
			"sum":	{
				"start":	6.400097,
				"end":	6.600251,
				"seconds":	0.20015400648117065,
				"bytes":	3145728,
				"bits_per_second":	125732302.05295669,
				"retransmits":	0,
				"omitted":	false,
				"sender":	true
			}
		}, {
			"streams":	[{
					"socket":	5,
					"start":	6.600251,
					"end":	6.800104,
					"seconds":	0.19985300302505493,
					"bytes":	3145728,
					"bits_per_second":	125921670.52323472,
					"retransmits":	0,
					"snd_cwnd":	324352,
					"snd_wnd":	1810048,
					"rtt":	21855,
					"rttvar":	192,
					"pmtu":	9001,
					"omitted":	false,
					"sender":	true
				}],
			"sum":	{
				"start":	6.600251,
				"end":	6.800104,
				"seconds":	0.19985300302505493,
				"bytes":	3145728,
				"bits_per_second":	125921670.52323472,
				"retransmits":	0,
				"omitted":	false,
				"sender":	true
			}
		}, {
			"streams":	[{
					"socket":	5,
					"start":	6.800104,
					"end":	7.000271,
					"seconds":	0.20016700029373169,
					"bytes":	3276800,
					"bits_per_second":	130962645.99825206,
					"retransmits":	0,
					"snd_cwnd":	328696,
					"snd_wnd":	1577728,
					"rtt":	22107,
					"rttvar":	267,
					"pmtu":	9001,
					"omitted":	false,
					"sender":	true
				}],
			"sum":	{
				"start":	6.800104,
				"end":	7.000271,
				"seconds":	0.20016700029373169,
				"bytes":	3276800,
				"bits_per_second":	130962645.99825206,
				"retransmits":	0,
				"omitted":	false,
				"sender":	true
			}
		}, {
			"streams":	[{
					"socket":	5,
					"start":	7.000271,
					"end":	7.200308,
					"seconds":	0.20003700256347656,
					"bytes":	3276800,
					"bits_per_second":	131047754.4857309,
					"retransmits":	0,
					"snd_cwnd":	333040,
					"snd_wnd":	1818624,
					"rtt":	21590,
					"rttvar":	353,
					"pmtu":	9001,
					"omitted":	false,
					"sender":	true
				}],
			"sum":	{
				"start":	7.000271,
				"end":	7.200308,
				"seconds":	0.20003700256347656,
				"bytes":	3276800,
				"bits_per_second":	131047754.4857309,
				"retransmits":	0,
				"omitted":	false,
				"sender":	true
			}
		}, {
			"streams":	[{
					"socket":	5,
					"start":	7.200308,
					"end":	7.40027,
					"seconds":	0.19996200501918793,
					"bytes":	1703936,
					"bits_per_second":	68170390.663426042,
					"retransmits":	0,
					"snd_cwnd":	337384,
					"snd_wnd":	1740800,
					"rtt":	21934,
					"rttvar":	112,
					"pmtu":	9001,
					"omitted":	false,
					"sender":	true
				}],
			"sum":	{
				"start":	7.200308,
				"end":	7.40027,
				"seconds":	0.19996200501918793,
				"bytes":	1703936,
				"bits_per_second":	68170390.663426042,
				"retransmits":	0,
				"omitted":	false,
				"sender":	true
			}
		}, {
			"streams":	[{
					"socket":	5,
					"start":	7.40027,
					"end":	7.600258,
					"seconds":	0.19998799264431,
					"bytes":	3014656,
					"bits_per_second":	120593480.04404391,
					"retransmits":	0,
					"snd_cwnd":	341728,
					"snd_wnd":	1818624,
					"rtt":	21206,
					"rttvar":	357,
					"pmtu":	9001,
					"omitted":	false,
					"sender":	true
				}],
			"sum":	{
				"start":	7.40027,
				"end":	7.600258,
				"seconds":	0.19998799264431,
				"bytes":	3014656,
				"bits_per_second":	120593480.04404391,
				"retransmits":	0,
				"omitted":	false,
				"sender":	true
			}
		}, {
			"streams":	[{
					"socket":	5,
					"start":	7.600258,
					"end":	7.800271,
					"seconds":	0.20001299679279327,
					"bytes":	3407872,
					"bits_per_second":	136306022.29435882,
					"retransmits":	0,
					"snd_cwnd":	346072,
					"snd_wnd":	1818624,
					"rtt":	21958,
					"rttvar":	192,
					"pmtu":	9001,
					"omitted":	false,
					"sender":	true
				}],
			"sum":	{
				"start":	7.600258,
				"end":	7.800271,
				"seconds":	0.20001299679279327,
				"bytes":	3407872,
				"bits_per_second":	136306022.29435882,
				"retransmits":	0,
				"omitted":	false,
				"sender":	true
			}
		}, {
			"streams":	[{
					"socket":	5,
					"start":	7.800271,
					"end":	8.000274,
					"seconds":	0.2000029981136322,
					"bytes":	3014656,
					"bits_per_second":	120584432.37084739,
					"retransmits":	0,
					"snd_cwnd":	351864,
					"snd_wnd":	1762432,
					"rtt":	21831,
					"rttvar":	197,
					"pmtu":	9001,
					"omitted":	false,
					"sender":	true
				}],
			"sum":	{
				"start":	7.800271,
				"end":	8.000274,
				"seconds":	0.2000029981136322,
				"bytes":	3014656,
				"bits_per_second":	120584432.37084739,
				"retransmits":	0,
				"omitted":	false,
				"sender":	true
			}
		}, {
			"streams":	[{
					"socket":	5,
					"start":	8.000274,
					"end":	8.200895,
					"seconds":	0.20062099397182465,
					"bytes":	4325376,
					"bits_per_second":	172479496.36247775,
					"retransmits":	0,
					"snd_cwnd":	359104,
					"snd_wnd":	1818624,
					"rtt":	21681,
					"rttvar":	333,
					"pmtu":	9001,
					"omitted":	false,
					"sender":	true
				}],
			"sum":	{
				"start":	8.000274,
				"end":	8.200895,
				"seconds":	0.20062099397182465,
				"bytes":	4325376,
				"bits_per_second":	172479496.36247775,
				"retransmits":	0,
				"omitted":	false,
				"sender":	true
			}
		}, {
			"streams":	[{
					"socket":	5,
					"start":	8.200895,
					"end":	8.400295,
					"seconds":	0.19939999282360077,
					"bytes":	2883584,
					"bits_per_second":	115690435.45757648,
					"retransmits":	0,
					"snd_cwnd":	367792,
					"snd_wnd":	1688832,
					"rtt":	21744,
					"rttvar":	371,
					"pmtu":	9001,
					"omitted":	false,
					"sender":	true
				}],
			"sum":	{
				"start":	8.200895,
				"end":	8.400295,
				"seconds":	0.19939999282360077,
				"bytes":	2883584,
				"bits_per_second":	115690435.45757648,
				"retransmits":	0,
				"omitted":	false,
				"sender":	true
			}
		}, {
			"streams":	[{
					"socket":	5,
					"start":	8.400295,
					"end":	8.601093,
					"seconds":	0.20079800486564636,
					"bytes":	2883584,
					"bits_per_second":	114884966.189954,
					"retransmits":	0,
					"snd_cwnd":	375032,
					"snd_wnd":	1818624,
					"rtt":	21974,
					"rttvar":	900,
					"pmtu":	9001,
					"omitted":	false,
					"sender":	true
				}],
			"sum":	{
				"start":	8.400295,
				"end":	8.601093,
				"seconds":	0.20079800486564636,
				"bytes":	2883584,
				"bits_per_second":	114884966.189954,
				"retransmits":	0,
				"omitted":	false,
				"sender":	true
			}
		}, {
			"streams":	[{
					"socket":	5,
					"start":	8.601093,
					"end":	8.800269,
					"seconds":	0.19917599856853485,
					"bytes":	4587520,
					"bits_per_second":	184259952.3223767,
					"retransmits":	0,
					"snd_cwnd":	380824,
					"snd_wnd":	1818624,
					"rtt":	21580,
					"rttvar":	251,
					"pmtu":	9001,
					"omitted":	false,
					"sender":	true
				}],
			"sum":	{
				"start":	8.601093,
				"end":	8.800269,
				"seconds":	0.19917599856853485,
				"bytes":	4587520,
				"bits_per_second":	184259952.3223767,
				"retransmits":	0,
				"omitted":	false,
				"sender":	true
			}
		}, {
			"streams":	[{
					"socket":	5,
					"start":	8.800269,
					"end":	9.000272,
					"seconds":	0.2000029981136322,
					"bytes":	3145728,
					"bits_per_second":	125827233.77827553,
					"retransmits":	0,
					"snd_cwnd":	386616,
					"snd_wnd":	1811456,
					"rtt":	21879,
					"rttvar":	209,
					"pmtu":	9001,
					"omitted":	false,
					"sender":	true
				}],
			"sum":	{
				"start":	8.800269,
				"end":	9.000272,
				"seconds":	0.2000029981136322,
				"bytes":	3145728,
				"bits_per_second":	125827233.77827553,
				"retransmits":	0,
				"omitted":	false,
				"sender":	true
			}
		}, {
			"streams":	[{
					"socket":	5,
					"start":	9.000272,
					"end":	9.200268,
					"seconds":	0.19999599456787109,
					"bytes":	3145728,
					"bits_per_second":	125831640.05046946,
					"retransmits":	0,
					"snd_cwnd":	395304,
					"snd_wnd":	1818624,
					"rtt":	21234,
					"rttvar":	249,
					"pmtu":	9001,
					"omitted":	false,
					"sender":	true
				}],
			"sum":	{
				"start":	9.000272,
				"end":	9.200268,
				"seconds":	0.19999599456787109,
				"bytes":	3145728,
				"bits_per_second":	125831640.05046946,
				"retransmits":	0,
				"omitted":	false,
				"sender":	true
			}
		}, {
			"streams":	[{
					"socket":	5,
					"start":	9.200268,
					"end":	9.400659,
					"seconds":	0.20039099454879761,
					"bytes":	3014656,
					"bits_per_second":	120350957.1590412,
					"retransmits":	0,
					"snd_cwnd":	401096,
					"snd_wnd":	1794176,
					"rtt":	21615,
					"rttvar":	526,
					"pmtu":	9001,
					"omitted":	false,
					"sender":	true
				}],
			"sum":	{
				"start":	9.200268,
				"end":	9.400659,
				"seconds":	0.20039099454879761,
				"bytes":	3014656,
				"bits_per_second":	120350957.1590412,
				"retransmits":	0,
				"omitted":	false,
				"sender":	true
			}
		}, {
			"streams":	[{
					"socket":	5,
					"start":	9.400659,
					"end":	9.600367,
					"seconds":	0.1997079998254776,
					"bytes":	4456448,
					"bits_per_second":	178518557.24936152,
					"retransmits":	0,
					"snd_cwnd":	408336,
					"snd_wnd":	1818624,
					"rtt":	21667,
					"rttvar":	446,
					"pmtu":	9001,
					"omitted":	false,
					"sender":	true
				}],
			"sum":	{
				"start":	9.400659,
				"end":	9.600367,
				"seconds":	0.1997079998254776,
				"bytes":	4456448,
				"bits_per_second":	178518557.24936152,
				"retransmits":	0,
				"omitted":	false,
				"sender":	true
			}
		}, {
			"streams":	[{
					"socket":	5,
					"start":	9.600367,
					"end":	9.800271,
					"seconds":	0.19990399479866028,
					"bytes":	3276800,
					"bits_per_second":	131134948.18551612,
					"retransmits":	0,
					"snd_cwnd":	415576,
					"snd_wnd":	1818624,
					"rtt":	22941,
					"rttvar":	2913,
					"pmtu":	9001,
					"omitted":	false,
					"sender":	true
				}],
			"sum":	{
				"start":	9.600367,
				"end":	9.800271,
				"seconds":	0.19990399479866028,
				"bytes":	3276800,
				"bits_per_second":	131134948.18551612,
				"retransmits":	0,
				"omitted":	false,
				"sender":	true
			}
		}, {
			"streams":	[{
					"socket":	5,
					"start":	9.800271,
					"end":	10.000146,
					"seconds":	0.19987499713897705,
					"bytes":	3276800,
					"bits_per_second":	131153973.109366,
					"retransmits":	0,
					"snd_cwnd":	422816,
					"snd_wnd":	1759488,
					"rtt":	22003,
					"rttvar":	90,
					"pmtu":	9001,
					"omitted":	false,
					"sender":	true
				}],
			"sum":	{
				"start":	9.800271,
				"end":	10.000146,
				"seconds":	0.19987499713897705,
				"bytes":	3276800,
				"bits_per_second":	131153973.109366,
				"retransmits":	0,
				"omitted":	false,
				"sender":	true
			}
		}, {
			"streams":	[{
					"socket":	5,
					"start":	10.000146,
					"end":	10.200254,
					"seconds":	0.20010800659656525,
					"bytes":	4980736,
					"bits_per_second":	199121907.60229149,
					"retransmits":	0,
					"snd_cwnd":	430056,
					"snd_wnd":	1808640,
					"rtt":	21806,
					"rttvar":	308,
					"pmtu":	9001,
					"omitted":	false,
					"sender":	true
				}],
			"sum":	{
				"start":	10.000146,
				"end":	10.200254,
				"seconds":	0.20010800659656525,
				"bytes":	4980736,
				"bits_per_second":	199121907.60229149,
				"retransmits":	0,
				"omitted":	false,
				"sender":	true
			}
		}, {
			"streams":	[{
					"socket":	5,
					"start":	10.200254,
					"end":	10.400116,
					"seconds":	0.199862003326416,
					"bytes":	3538944,
					"bits_per_second":	141655499.93893224,
					"retransmits":	13,
					"snd_cwnd":	308424,
					"snd_wnd":	1721984,
					"rtt":	21971,
					"rttvar":	35,
					"pmtu":	9001,
					"omitted":	false,
					"sender":	true
				}],
			"sum":	{
				"start":	10.200254,
				"end":	10.400116,
				"seconds":	0.199862003326416,
				"bytes":	3538944,
				"bits_per_second":	141655499.93893224,
				"retransmits":	13,
				"omitted":	false,
				"sender":	true
			}
		}, {
			"streams":	[{
					"socket":	5,
					"start":	10.400116,
					"end":	10.600272,
					"seconds":	0.20015600323677063,
					"bytes":	1441792,
					"bits_per_second":	57626730.217807569,
					"retransmits":	0,
					"snd_cwnd":	320008,
					"snd_wnd":	1818624,
					"rtt":	21390,
					"rttvar":	238,
					"pmtu":	9001,
					"omitted":	false,
					"sender":	true
				}],
			"sum":	{
				"start":	10.400116,
				"end":	10.600272,
				"seconds":	0.20015600323677063,
				"bytes":	1441792,
				"bits_per_second":	57626730.217807569,
				"retransmits":	0,
				"omitted":	false,
				"sender":	true
			}
		}, {
			"streams":	[{
					"socket":	5,
					"start":	10.600272,
					"end":	10.800291,
					"seconds":	0.20001900196075439,
					"bytes":	4325376,
					"bits_per_second":	172998603.43663466,
					"retransmits":	0,
					"snd_cwnd":	331592,
					"snd_wnd":	1805696,
					"rtt":	21193,
					"rttvar":	435,
					"pmtu":	9001,
					"omitted":	false,
					"sender":	true
				}],
			"sum":	{
				"start":	10.600272,
				"end":	10.800291,
				"seconds":	0.20001900196075439,
				"bytes":	4325376,
				"bits_per_second":	172998603.43663466,
				"retransmits":	0,
				"omitted":	false,
				"sender":	true
			}
		}, {
			"streams":	[{
					"socket":	5,
					"start":	10.800291,
					"end":	11.000272,
					"seconds":	0.19998100399971008,
					"bytes":	3014656,
					"bits_per_second":	120597694.369186,
					"retransmits":	0,
					"snd_cwnd":	341728,
					"snd_wnd":	1657088,
					"rtt":	21652,
					"rttvar":	162,
					"pmtu":	9001,
					"omitted":	false,
					"sender":	true
				}],
			"sum":	{
				"start":	10.800291,
				"end":	11.000272,
				"seconds":	0.19998100399971008,
				"bytes":	3014656,
				"bits_per_second":	120597694.369186,
				"retransmits":	0,
				"omitted":	false,
				"sender":	true
			}
		}, {
			"streams":	[{
					"socket":	5,
					"start":	11.000272,
					"end":	11.200099,
					"seconds":	0.19982700049877167,
					"bytes":	2883584,
					"bits_per_second":	115443218.09575379,
					"retransmits":	0,
					"snd_cwnd":	351864,
					"snd_wnd":	1772544,
					"rtt":	21893,
					"rttvar":	414,
					"pmtu":	9001,
					"omitted":	false,
					"sender":	true
				}],
			"sum":	{
				"start":	11.000272,
				"end":	11.200099,
				"seconds":	0.19982700049877167,
				"bytes":	2883584,
				"bits_per_second":	115443218.09575379,
				"retransmits":	0,
				"omitted":	false,
				"sender":	true
			}
		}, {
			"streams":	[{
					"socket":	5,
					"start":	11.200099,
					"end":	11.400207,
					"seconds":	0.20010800659656525,
					"bytes":	3014656,
					"bits_per_second":	120521154.60138695,
					"retransmits":	0,
					"snd_cwnd":	360552,
					"snd_wnd":	1818624,
					"rtt":	21022,
					"rttvar":	486,
					"pmtu":	9001,
					"omitted":	false,
					"sender":	true
				}],
			"sum":	{
				"start":	11.200099,
				"end":	11.400207,
				"seconds":	0.20010800659656525,
				"bytes":	3014656,
				"bits_per_second":	120521154.60138695,
				"retransmits":	0,
				"omitted":	false,
				"sender":	true
			}
		}, {
			"streams":	[{
					"socket":	5,
					"start":	11.400207,
					"end":	11.600129,
					"seconds":	0.19992199540138245,
					"bytes":	2883584,
					"bits_per_second":	115388364.11513969,
					"retransmits":	0,
					"snd_cwnd":	369240,
					"snd_wnd":	1799936,
					"rtt":	21049,
					"rttvar":	606,
					"pmtu":	9001,
					"omitted":	false,
					"sender":	true
				}],
			"sum":	{
				"start":	11.400207,
				"end":	11.600129,
				"seconds":	0.19992199540138245,
				"bytes":	2883584,
				"bits_per_second":	115388364.11513969,
				"retransmits":	0,
				"omitted":	false,
				"sender":	true
			}
		}, {
			"streams":	[{
					"socket":	5,
					"start":	11.600129,
					"end":	11.800091,
					"seconds":	0.19996200501918793,
					"bytes":	4456448,
					"bits_per_second":	178291790.96588349,
					"retransmits":	0,
					"snd_cwnd":	376480,
					"snd_wnd":	1808640,
					"rtt":	22021,
					"rttvar":	219,
					"pmtu":	9001,
					"omitted":	false,
					"sender":	true
				}],
			"sum":	{
				"start":	11.600129,
				"end":	11.800091,
				"seconds":	0.19996200501918793,
				"bytes":	4456448,
				"bits_per_second":	178291790.96588349,
				"retransmits":	0,
				"omitted":	false,
				"sender":	true
			}
		}, {
			"streams":	[{
					"socket":	5,
					"start":	11.800091,
					"end":	12.000101,
					"seconds":	0.20001000165939331,
					"bytes":	3014656,
					"bits_per_second":	120580209.98905058,
					"retransmits":	0,
					"snd_cwnd":	386616,
					"snd_wnd":	1818624,
					"rtt":	22630,
					"rttvar":	436,
					"pmtu":	9001,
					"omitted":	false,
					"sender":	true
				}],
			"sum":	{
				"start":	11.800091,
				"end":	12.000101,
				"seconds":	0.20001000165939331,
				"bytes":	3014656,
				"bits_per_second":	120580209.98905058,
				"retransmits":	0,
				"omitted":	false,
				"sender":	true
			}
		}, {
			"streams":	[{
					"socket":	5,
					"start":	12.000101,
					"end":	12.201098,
					"seconds":	0.200996994972229,
					"bytes":	3145728,
					"bits_per_second":	125204976.34045258,
					"retransmits":	0,
					"snd_cwnd":	389512,
					"snd_wnd":	1811456,
					"rtt":	21831,
					"rttvar":	116,
					"pmtu":	9001,
					"omitted":	false,
					"sender":	true
				}],
			"sum":	{
				"start":	12.000101,
				"end":	12.201098,
				"seconds":	0.200996994972229,
				"bytes":	3145728,
				"bits_per_second":	125204976.34045258,
				"retransmits":	0,
				"omitted":	false,
				"sender":	true
			}
		}, {
			"streams":	[{
					"socket":	5,
					"start":	12.201098,
					"end":	12.400264,
					"seconds":	0.19916599988937378,
					"bytes":	3145728,
					"bits_per_second":	126356024.69286068,
					"retransmits":	0,
					"snd_cwnd":	398200,
					"snd_wnd":	1781120,
					"rtt":	21548,
					"rttvar":	467,
					"pmtu":	9001,
					"omitted":	false,
					"sender":	true
				}],
			"sum":	{
				"start":	12.201098,
				"end":	12.400264,
				"seconds":	0.19916599988937378,
				"bytes":	3145728,
				"bits_per_second":	126356024.69286068,
				"retransmits":	0,
				"omitted":	false,
				"sender":	true
			}
		}, {
			"streams":	[{
					"socket":	5,
					"start":	12.400264,
					"end":	12.600536,
					"seconds":	0.20027199387550354,
					"bytes":	4587520,
					"bits_per_second":	183251583.45811534,
					"retransmits":	0,
					"snd_cwnd":	401096,
					"snd_wnd":	1818624,
					"rtt":	21968,
					"rttvar":	364,
					"pmtu":	9001,
					"omitted":	false,
					"sender":	true
				}],
			"sum":	{
				"start":	12.400264,
				"end":	12.600536,
				"seconds":	0.20027199387550354,
				"bytes":	4587520,
				"bits_per_second":	183251583.45811534,
				"retransmits":	0,
				"omitted":	false,
				"sender":	true
			}
		}, {
			"streams":	[{
					"socket":	5,
					"start":	12.600536,
					"end":	12.800514,
					"seconds":	0.19997799396514893,
					"bytes":	3014656,
					"bits_per_second":	120599509.58505476,
					"retransmits":	2,
					"snd_cwnd":	286704,
					"snd_wnd":	1818624,
					"rtt":	21742,
					"rttvar":	385,
					"pmtu":	9001,
					"omitted":	false,
					"sender":	true
				}],
			"sum":	{
				"start":	12.600536,
				"end":	12.800514,
				"seconds":	0.19997799396514893,
				"bytes":	3014656,
				"bits_per_second":	120599509.58505476,
				"retransmits":	2,
				"omitted":	false,
				"sender":	true
			}
		}, {
			"streams":	[{
					"socket":	5,
					"start":	12.800514,
					"end":	13.000275,
					"seconds":	0.19976100325584412,
					"bytes":	1572864,
					"bits_per_second":	62989831.823603839,
					"retransmits":	0,
					"snd_cwnd":	293944,
					"snd_wnd":	1818624,
					"rtt":	21100,
					"rttvar":	411,
					"pmtu":	9001,
					"omitted":	false,
					"sender":	true
				}],
			"sum":	{
				"start":	12.800514,
				"end":	13.000275,
				"seconds":	0.19976100325584412,
				"bytes":	1572864,
				"bits_per_second":	62989831.823603839,
				"retransmits":	0,
				"omitted":	false,
				"sender":	true
			}
		}, {
			"streams":	[{
					"socket":	5,
					"start":	13.000275,
					"end":	13.200267,
					"seconds":	0.19999200105667114,
					"bytes":	2883584,
					"bits_per_second":	115347973.309508,
					"retransmits":	0,
					"snd_cwnd":	301184,
					"snd_wnd":	1805696,
					"rtt":	21653,
					"rttvar":	363,
					"pmtu":	9001,
					"omitted":	false,
					"sender":	true
				}],
			"sum":	{
				"start":	13.000275,
				"end":	13.200267,
				"seconds":	0.19999200105667114,
				"bytes":	2883584,
				"bits_per_second":	115347973.309508,
				"retransmits":	0,
				"omitted":	false,
				"sender":	true
			}
		}, {
			"streams":	[{
					"socket":	5,
					"start":	13.200267,
					"end":	13.40115,
					"seconds":	0.20088300108909607,
					"bytes":	3014656,
					"bits_per_second":	120056191.26181546,
					"retransmits":	0,
					"snd_cwnd":	306976,
					"snd_wnd":	1802752,
					"rtt":	21391,
					"rttvar":	573,
					"pmtu":	9001,
					"omitted":	false,
					"sender":	true
				}],
			"sum":	{
				"start":	13.200267,
				"end":	13.40115,
				"seconds":	0.20088300108909607,
				"bytes":	3014656,
				"bits_per_second":	120056191.26181546,
				"retransmits":	0,
				"omitted":	false,
				"sender":	true
			}
		}, {
			"streams":	[{
					"socket":	5,
					"start":	13.40115,
					"end":	13.600104,
					"seconds":	0.19895400106906891,
					"bytes":	2883584,
					"bits_per_second":	115949776.71241443,
					"retransmits":	0,
					"snd_cwnd":	312768,
					"snd_wnd":	1736448,
					"rtt":	21732,
					"rttvar":	394,
					"pmtu":	9001,
					"omitted":	false,
					"sender":	true
				}],
			"sum":	{
				"start":	13.40115,
				"end":	13.600104,
				"seconds":	0.19895400106906891,
				"bytes":	2883584,
				"bits_per_second":	115949776.71241443,
				"retransmits":	0,
				"omitted":	false,
				"sender":	true
			}
		}, {
			"streams":	[{
					"socket":	5,
					"start":	13.600104,
					"end":	13.8011,
					"seconds":	0.200995996594429,
					"bytes":	3014656,
					"bits_per_second":	119988698.32548921,
					"retransmits":	0,
					"snd_cwnd":	320008,
					"snd_wnd":	1818624,
					"rtt":	22248,
					"rttvar":	596,
					"pmtu":	9001,
					"omitted":	false,
					"sender":	true
				}],
			"sum":	{
				"start":	13.600104,
				"end":	13.8011,
				"seconds":	0.200995996594429,
				"bytes":	3014656,
				"bits_per_second":	119988698.32548921,
				"retransmits":	0,
				"omitted":	false,
				"sender":	true
			}
		}, {
			"streams":	[{
					"socket":	5,
					"start":	13.8011,
					"end":	14.000266,
					"seconds":	0.19916599988937378,
					"bytes":	3276800,
					"bits_per_second":	131620859.0550632,
					"retransmits":	0,
					"snd_cwnd":	327248,
					"snd_wnd":	1818624,
					"rtt":	21678,
					"rttvar":	471,
					"pmtu":	9001,
					"omitted":	false,
					"sender":	true
				}],
			"sum":	{
				"start":	13.8011,
				"end":	14.000266,
				"seconds":	0.19916599988937378,
				"bytes":	3276800,
				"bits_per_second":	131620859.0550632,
				"retransmits":	0,
				"omitted":	false,
				"sender":	true
			}
		}, {
			"streams":	[{
					"socket":	5,
					"start":	14.000266,
					"end":	14.20029,
					"seconds":	0.20002399384975433,
					"bytes":	3145728,
					"bits_per_second":	125814026.18579355,
					"retransmits":	0,
					"snd_cwnd":	334488,
					"snd_wnd":	1776896,
					"rtt":	21675,
					"rttvar":	284,
					"pmtu":	9001,
					"omitted":	false,
					"sender":	true
				}],
			"sum":	{
				"start":	14.000266,
				"end":	14.20029,
				"seconds":	0.20002399384975433,
				"bytes":	3145728,
				"bits_per_second":	125814026.18579355,
				"retransmits":	0,
				"omitted":	false,
				"sender":	true
			}
		}, {
			"streams":	[{
					"socket":	5,
					"start":	14.20029,
					"end":	14.40026,
					"seconds":	0.199970006942749,
					"bytes":	3145728,
					"bits_per_second":	125847992.8302694,
					"retransmits":	0,
					"snd_cwnd":	341728,
					"snd_wnd":	1818624,
					"rtt":	21755,
					"rttvar":	179,
					"pmtu":	9001,
					"omitted":	false,
					"sender":	true
				}],
			"sum":	{
				"start":	14.20029,
				"end":	14.40026,
				"seconds":	0.199970006942749,
				"bytes":	3145728,
				"bits_per_second":	125847992.8302694,
				"retransmits":	0,
				"omitted":	false,
				"sender":	true
			}
		}, {
			"streams":	[{
					"socket":	5,
					"start":	14.40026,
					"end":	14.600258,
					"seconds":	0.19999800622463226,
					"bytes":	3145728,
					"bits_per_second":	125830374.38750483,
					"retransmits":	0,
					"snd_cwnd":	350416,
					"snd_wnd":	1753728,
					"rtt":	22056,
					"rttvar":	470,
					"pmtu":	9001,
					"omitted":	false,
					"sender":	true
				}],
			"sum":	{
				"start":	14.40026,
				"end":	14.600258,
				"seconds":	0.19999800622463226,
				"bytes":	3145728,
				"bits_per_second":	125830374.38750483,
				"retransmits":	0,
				"omitted":	false,
				"sender":	true
			}
		}, {
			"streams":	[{
					"socket":	5,
					"start":	14.600258,
					"end":	14.800744,
					"seconds":	0.20048600435256958,
					"bytes":	3145728,
					"bits_per_second":	125524093.72049743,
					"retransmits":	0,
					"snd_cwnd":	354760,
					"snd_wnd":	1818624,
					"rtt":	21906,
					"rttvar":	117,
					"pmtu":	9001,
					"omitted":	false,
					"sender":	true
				}],
			"sum":	{
				"start":	14.600258,
				"end":	14.800744,
				"seconds":	0.20048600435256958,
				"bytes":	3145728,
				"bits_per_second":	125524093.72049743,
				"retransmits":	0,
				"omitted":	false,
				"sender":	true
			}
		}, {
			"streams":	[{
					"socket":	5,
					"start":	14.800744,
					"end":	15.000268,
					"seconds":	0.199524000287056,
					"bytes":	2883584,
					"bits_per_second":	115618531.94007242,
					"retransmits":	0,
					"snd_cwnd":	362000,
					"snd_wnd":	1818624,
					"rtt":	21527,
					"rttvar":	149,
					"pmtu":	9001,
					"omitted":	false,
					"sender":	true
				}],
			"sum":	{
				"start":	14.800744,
				"end":	15.000268,
				"seconds":	0.199524000287056,
				"bytes":	2883584,
				"bits_per_second":	115618531.94007242,
				"retransmits":	0,
				"omitted":	false,
				"sender":	true
			}
		}, {
			"streams":	[{
					"socket":	5,
					"start":	15.000268,
					"end":	15.200273,
					"seconds":	0.20000499486923218,
					"bytes":	2883584,
					"bits_per_second":	115340479.44693993,
					"retransmits":	0,
					"snd_cwnd":	369240,
					"snd_wnd":	1799936,
					"rtt":	21507,
					"rttvar":	242,
					"pmtu":	9001,
					"omitted":	false,
					"sender":	true
				}],
			"sum":	{
				"start":	15.000268,
				"end":	15.200273,
				"seconds":	0.20000499486923218,
				"bytes":	2883584,
				"bits_per_second":	115340479.44693993,
				"retransmits":	0,
				"omitted":	false,
				"sender":	true
			}
		}, {
			"streams":	[{
					"socket":	5,
					"start":	15.200273,
					"end":	15.400381,
					"seconds":	0.20010800659656525,
					"bytes":	2883584,
					"bits_per_second":	115281104.40132666,
					"retransmits":	0,
					"snd_cwnd":	376480,
					"snd_wnd":	1818624,
					"rtt":	21484,
					"rttvar":	970,
					"pmtu":	9001,
					"omitted":	false,
					"sender":	true
				}],
			"sum":	{
				"start":	15.200273,
				"end":	15.400381,
				"seconds":	0.20010800659656525,
				"bytes":	2883584,
				"bits_per_second":	115281104.40132666,
				"retransmits":	0,
				"omitted":	false,
				"sender":	true
			}
		}, {
			"streams":	[{
					"socket":	5,
					"start":	15.400381,
					"end":	15.601097,
					"seconds":	0.20071600377559662,
					"bytes":	4456448,
					"bits_per_second":	177622029.78024107,
					"retransmits":	0,
					"snd_cwnd":	383720,
					"snd_wnd":	1818624,
					"rtt":	21702,
					"rttvar":	197,
					"pmtu":	9001,
					"omitted":	false,
					"sender":	true
				}],
			"sum":	{
				"start":	15.400381,
				"end":	15.601097,
				"seconds":	0.20071600377559662,
				"bytes":	4456448,
				"bits_per_second":	177622029.78024107,
				"retransmits":	0,
				"omitted":	false,
				"sender":	true
			}
		}, {
			"streams":	[{
					"socket":	5,
					"start":	15.601097,
					"end":	15.8006,
					"seconds":	0.19950300455093384,
					"bytes":	3276800,
					"bits_per_second":	131398522.33808023,
					"retransmits":	0,
					"snd_cwnd":	389512,
					"snd_wnd":	1814400,
					"rtt":	22068,
					"rttvar":	227,
					"pmtu":	9001,
					"omitted":	false,
					"sender":	true
				}],
			"sum":	{
				"start":	15.601097,
				"end":	15.8006,
				"seconds":	0.19950300455093384,
				"bytes":	3276800,
				"bits_per_second":	131398522.33808023,
				"retransmits":	0,
				"omitted":	false,
				"sender":	true
			}
		}, {
			"streams":	[{
					"socket":	5,
					"start":	15.8006,
					"end":	16.000095,
					"seconds":	0.19949500262737274,
					"bytes":	3145728,
					"bits_per_second":	126147641.13668576,
					"retransmits":	0,
					"snd_cwnd":	399648,
					"snd_wnd":	1818624,
					"rtt":	21923,
					"rttvar":	127,
					"pmtu":	9001,
					"omitted":	false,
					"sender":	true
				}],
			"sum":	{
				"start":	15.8006,
				"end":	16.000095,
				"seconds":	0.19949500262737274,
				"bytes":	3145728,
				"bits_per_second":	126147641.13668576,
				"retransmits":	0,
				"omitted":	false,
				"sender":	true
			}
		}, {
			"streams":	[{
					"socket":	5,
					"start":	16.000095,
					"end":	16.200252,
					"seconds":	0.20015700161457062,
					"bytes":	3014656,
					"bits_per_second":	120491653.07962108,
					"retransmits":	4,
					"snd_cwnd":	289600,
					"snd_wnd":	1818624,
					"rtt":	21623,
					"rttvar":	569,
					"pmtu":	9001,
					"omitted":	false,
					"sender":	true
				}],
			"sum":	{
				"start":	16.000095,
				"end":	16.200252,
				"seconds":	0.20015700161457062,
				"bytes":	3014656,
				"bits_per_second":	120491653.07962108,
				"retransmits":	4,
				"omitted":	false,
				"sender":	true
			}
		}, {
			"streams":	[{
					"socket":	5,
					"start":	16.200252,
					"end":	16.40026,
					"seconds":	0.20000800490379333,
					"bytes":	2752512,
					"bits_per_second":	110096073.45761974,
					"retransmits":	0,
					"snd_cwnd":	299736,
					"snd_wnd":	1818624,
					"rtt":	21570,
					"rttvar":	411,
					"pmtu":	9001,
					"omitted":	false,
					"sender":	true
				}],
			"sum":	{
				"start":	16.200252,
				"end":	16.40026,
				"seconds":	0.20000800490379333,
				"bytes":	2752512,
				"bits_per_second":	110096073.45761974,
				"retransmits":	0,
				"omitted":	false,
				"sender":	true
			}
		}, {
			"streams":	[{
					"socket":	5,
					"start":	16.40026,
					"end":	16.600252,
					"seconds":	0.19999200105667114,
					"bytes":	3014656,
					"bits_per_second":	120591063.00539473,
					"retransmits":	0,
					"snd_cwnd":	309872,
					"snd_wnd":	1818624,
					"rtt":	21001,
					"rttvar":	455,
					"pmtu":	9001,
					"omitted":	false,
					"sender":	true
				}],
			"sum":	{
				"start":	16.40026,
				"end":	16.600252,
				"seconds":	0.19999200105667114,
				"bytes":	3014656,
				"bits_per_second":	120591063.00539473,
				"retransmits":	0,
				"omitted":	false,
				"sender":	true
			}
		}, {
			"streams":	[{
					"socket":	5,
					"start":	16.600252,
					"end":	16.800327,
					"seconds":	0.20007500052452087,
					"bytes":	3145728,
					"bits_per_second":	125781951.43833433,
					"retransmits":	0,
					"snd_cwnd":	318560,
					"snd_wnd":	1818624,
					"rtt":	21355,
					"rttvar":	768,
					"pmtu":	9001,
					"omitted":	false,
					"sender":	true
				}],
			"sum":	{
				"start":	16.600252,
				"end":	16.800327,
				"seconds":	0.20007500052452087,
				"bytes":	3145728,
				"bits_per_second":	125781951.43833433,
				"retransmits":	0,
				"omitted":	false,
				"sender":	true
			}
		}, {
			"streams":	[{
					"socket":	5,
					"start":	16.800327,
					"end":	17.00028,
					"seconds":	0.19995300471782684,
					"bytes":	1703936,
					"bits_per_second":	68173459.1547485,
					"retransmits":	0,
					"snd_cwnd":	330144,
					"snd_wnd":	1664256,
					"rtt":	22386,
					"rttvar":	552,
					"pmtu":	9001,
					"omitted":	false,
					"sender":	true
				}],
			"sum":	{
				"start":	16.800327,
				"end":	17.00028,
				"seconds":	0.19995300471782684,
				"bytes":	1703936,
				"bits_per_second":	68173459.1547485,
				"retransmits":	0,
				"omitted":	false,
				"sender":	true
			}
		}, {
			"streams":	[{
					"socket":	5,
					"start":	17.00028,
					"end":	17.200264,
					"seconds":	0.19998399913311005,
					"bytes":	3276800,
					"bits_per_second":	131082487.16714382,
					"retransmits":	0,
					"snd_cwnd":	338832,
					"snd_wnd":	1818624,
					"rtt":	22269,
					"rttvar":	523,
					"pmtu":	9001,
					"omitted":	false,
					"sender":	true
				}],
			"sum":	{
				"start":	17.00028,
				"end":	17.200264,
				"seconds":	0.19998399913311005,
				"bytes":	3276800,
				"bits_per_second":	131082487.16714382,
				"retransmits":	0,
				"omitted":	false,
				"sender":	true
			}
		}, {
			"streams":	[{
					"socket":	5,
					"start":	17.200264,
					"end":	17.400106,
					"seconds":	0.19984200596809387,
					"bytes":	3276800,
					"bits_per_second":	131175624.82927291,
					"retransmits":	0,
					"snd_cwnd":	344624,
					"snd_wnd":	1818624,
					"rtt":	21903,
					"rttvar":	107,
					"pmtu":	9001,
					"omitted":	false,
					"sender":	true
				}],
			"sum":	{
				"start":	17.200264,
				"end":	17.400106,
				"seconds":	0.19984200596809387,
				"bytes":	3276800,
				"bits_per_second":	131175624.82927291,
				"retransmits":	0,
				"omitted":	false,
				"sender":	true
			}
		}, {
			"streams":	[{
					"socket":	5,
					"start":	17.400106,
					"end":	17.600729,
					"seconds":	0.20062300562858582,
					"bytes":	2883584,
					"bits_per_second":	114985177.93471366,
					"retransmits":	12,
					"snd_cwnd":	246160,
					"snd_wnd":	1801344,
					"rtt":	22015,
					"rttvar":	317,
					"pmtu":	9001,
					"omitted":	false,
					"sender":	true
				}],
			"sum":	{
				"start":	17.400106,
				"end":	17.600729,
				"seconds":	0.20062300562858582,
				"bytes":	2883584,
				"bits_per_second":	114985177.93471366,
				"retransmits":	12,
				"omitted":	false,
				"sender":	true
			}
		}, {
			"streams":	[{
					"socket":	5,
					"start":	17.600729,
					"end":	17.800622,
					"seconds":	0.19989299774169922,
					"bytes":	3145728,
					"bits_per_second":	125896476.03623994,
					"retransmits":	0,
					"snd_cwnd":	254848,
					"snd_wnd":	1818624,
					"rtt":	21900,
					"rttvar":	488,
					"pmtu":	9001,
					"omitted":	false,
					"sender":	true
				}],
			"sum":	{
				"start":	17.600729,
				"end":	17.800622,
				"seconds":	0.19989299774169922,
				"bytes":	3145728,
				"bits_per_second":	125896476.03623994,
				"retransmits":	0,
				"omitted":	false,
				"sender":	true
			}
		}, {
			"streams":	[{
					"socket":	5,
					"start":	17.800622,
					"end":	18.000265,
					"seconds":	0.19964300096035,
					"bytes":	1441792,
					"bits_per_second":	57774807.75442145,
					"retransmits":	0,
					"snd_cwnd":	260640,
					"snd_wnd":	1818624,
					"rtt":	21981,
					"rttvar":	31,
					"pmtu":	9001,
					"omitted":	false,
					"sender":	true
				}],
			"sum":	{
				"start":	17.800622,
				"end":	18.000265,
				"seconds":	0.19964300096035,
				"bytes":	1441792,
				"bits_per_second":	57774807.75442145,
				"retransmits":	0,
				"omitted":	false,
				"sender":	true
			}
		}, {
			"streams":	[{
					"socket":	5,
					"start":	18.000265,
					"end":	18.20027,
					"seconds":	0.20000499486923218,
					"bytes":	3014656,
					"bits_per_second":	120583228.51270993,
					"retransmits":	0,
					"snd_cwnd":	264984,
					"snd_wnd":	1818624,
					"rtt":	21065,
					"rttvar":	343,
					"pmtu":	9001,
					"omitted":	false,
					"sender":	true
				}],
			"sum":	{
				"start":	18.000265,
				"end":	18.20027,
				"seconds":	0.20000499486923218,
				"bytes":	3014656,
				"bits_per_second":	120583228.51270993,
				"retransmits":	0,
				"omitted":	false,
				"sender":	true
			}
		}, {
			"streams":	[{
					"socket":	5,
					"start":	18.20027,
					"end":	18.400104,
					"seconds":	0.19983400404453278,
					"bytes":	2883584,
					"bits_per_second":	115439172.17842051,
					"retransmits":	0,
					"snd_cwnd":	272224,
					"snd_wnd":	1753728,
					"rtt":	21548,
					"rttvar":	564,
					"pmtu":	9001,
					"omitted":	false,
					"sender":	true
				}],
			"sum":	{
				"start":	18.20027,
				"end":	18.400104,
				"seconds":	0.19983400404453278,
				"bytes":	2883584,
				"bits_per_second":	115439172.17842051,
				"retransmits":	0,
				"omitted":	false,
				"sender":	true
			}
		}, {
			"streams":	[{
					"socket":	5,
					"start":	18.400104,
					"end":	18.600387,
					"seconds":	0.20028300583362579,
					"bytes":	1572864,
					"bits_per_second":	62825659.858792856,
					"retransmits":	0,
					"snd_cwnd":	279464,
					"snd_wnd":	1818624,
					"rtt":	21520,
					"rttvar":	347,
					"pmtu":	9001,
					"omitted":	false,
					"sender":	true
				}],
			"sum":	{
				"start":	18.400104,
				"end":	18.600387,
				"seconds":	0.20028300583362579,
				"bytes":	1572864,
				"bits_per_second":	62825659.858792856,
				"retransmits":	0,
				"omitted":	false,
				"sender":	true
			}
		}, {
			"streams":	[{
					"socket":	5,
					"start":	18.600387,
					"end":	18.800259,
					"seconds":	0.19987200200557709,
					"bytes":	2752512,
					"bits_per_second":	110170988.3277477,
					"retransmits":	0,
					"snd_cwnd":	286704,
					"snd_wnd":	1818624,
					"rtt":	21477,
					"rttvar":	348,
					"pmtu":	9001,
					"omitted":	false,
					"sender":	true
				}],
			"sum":	{
				"start":	18.600387,
				"end":	18.800259,
				"seconds":	0.19987200200557709,
				"bytes":	2752512,
				"bits_per_second":	110170988.3277477,
				"retransmits":	0,
				"omitted":	false,
				"sender":	true
			}
		}, {
			"streams":	[{
					"socket":	5,
					"start":	18.800259,
					"end":	19.000264,
					"seconds":	0.20000499486923218,
					"bytes":	2883584,
					"bits_per_second":	115340479.44693993,
					"retransmits":	0,
					"snd_cwnd":	293944,
					"snd_wnd":	1818624,
					"rtt":	21808,
					"rttvar":	454,
					"pmtu":	9001,
					"omitted":	false,
					"sender":	true
				}],
			"sum":	{
				"start":	18.800259,
				"end":	19.000264,
				"seconds":	0.20000499486923218,
				"bytes":	2883584,
				"bits_per_second":	115340479.44693993,
				"retransmits":	0,
				"omitted":	false,
				"sender":	true
			}
		}, {
			"streams":	[{
					"socket":	5,
					"start":	19.000264,
					"end":	19.200539,
					"seconds":	0.2002750039100647,
					"bytes":	2883584,
					"bits_per_second":	115184978.40279257,
					"retransmits":	0,
					"snd_cwnd":	301184,
					"snd_wnd":	1664256,
					"rtt":	22234,
					"rttvar":	510,
					"pmtu":	9001,
					"omitted":	false,
					"sender":	true
				}],
			"sum":	{
				"start":	19.000264,
				"end":	19.200539,
				"seconds":	0.2002750039100647,
				"bytes":	2883584,
				"bits_per_second":	115184978.40279257,
				"retransmits":	0,
				"omitted":	false,
				"sender":	true
			}
		}, {
			"streams":	[{
					"socket":	5,
					"start":	19.200539,
					"end":	19.400266,
					"seconds":	0.19972699880599976,
					"bytes":	3014656,
					"bits_per_second":	120751065.92587283,
					"retransmits":	0,
					"snd_cwnd":	306976,
					"snd_wnd":	1684480,
					"rtt":	21705,
					"rttvar":	440,
					"pmtu":	9001,
					"omitted":	false,
					"sender":	true
				}],
			"sum":	{
				"start":	19.200539,
				"end":	19.400266,
				"seconds":	0.19972699880599976,
				"bytes":	3014656,
				"bits_per_second":	120751065.92587283,
				"retransmits":	0,
				"omitted":	false,
				"sender":	true
			}
		}, {
			"streams":	[{
					"socket":	5,
					"start":	19.400266,
					"end":	19.600246,
					"seconds":	0.1999800056219101,
					"bytes":	3014656,
					"bits_per_second":	120598296.43968007,
					"retransmits":	0,
					"snd_cwnd":	315664,
					"snd_wnd":	1818624,
					"rtt":	20718,
					"rttvar":	377,
					"pmtu":	9001,
					"omitted":	false,
					"sender":	true
				}],
			"sum":	{
				"start":	19.400266,
				"end":	19.600246,
				"seconds":	0.1999800056219101,
				"bytes":	3014656,
				"bits_per_second":	120598296.43968007,
				"retransmits":	0,
				"omitted":	false,
				"sender":	true
			}
		}, {
			"streams":	[{
					"socket":	5,
					"start":	19.600246,
					"end":	19.800249,
					"seconds":	0.2000029981136322,
					"bytes":	3014656,
					"bits_per_second":	120584432.37084739,
					"retransmits":	0,
					"snd_cwnd":	321456,
					"snd_wnd":	1802752,
					"rtt":	21439,
					"rttvar":	504,
					"pmtu":	9001,
					"omitted":	false,
					"sender":	true
				}],
			"sum":	{
				"start":	19.600246,
				"end":	19.800249,
				"seconds":	0.2000029981136322,
				"bytes":	3014656,
				"bits_per_second":	120584432.37084739,
				"retransmits":	0,
				"omitted":	false,
				"sender":	true
			}
		}, {
			"streams":	[{
					"socket":	5,
					"start":	19.800249,
					"end":	20.000494,
					"seconds":	0.20024499297142029,
					"bytes":	1572864,
					"bits_per_second":	62837586.1652425,
					"retransmits":	0,
					"snd_cwnd":	328696,
					"snd_wnd":	1818624,
					"rtt":	21175,
					"rttvar":	309,
					"pmtu":	9001,
					"omitted":	false,
					"sender":	true
				}],
			"sum":	{
				"start":	19.800249,
				"end":	20.000494,
				"seconds":	0.20024499297142029,
				"bytes":	1572864,
				"bits_per_second":	62837586.1652425,
				"retransmits":	0,
				"omitted":	false,
				"sender":	true
			}
		}, {
			"streams":	[{
					"socket":	5,
					"start":	20.000494,
					"end":	20.200808,
					"seconds":	0.200314000248909,
					"bytes":	3276800,
					"bits_per_second":	130866539.37031931,
					"retransmits":	0,
					"snd_cwnd":	334488,
					"snd_wnd":	1752320,
					"rtt":	21229,
					"rttvar":	302,
					"pmtu":	9001,
					"omitted":	false,
					"sender":	true
				}],
			"sum":	{
				"start":	20.000494,
				"end":	20.200808,
				"seconds":	0.200314000248909,
				"bytes":	3276800,
				"bits_per_second":	130866539.37031931,
				"retransmits":	0,
				"omitted":	false,
				"sender":	true
			}
		}, {
			"streams":	[{
					"socket":	5,
					"start":	20.200808,
					"end":	20.400285,
					"seconds":	0.19947700202465057,
					"bytes":	3145728,
					"bits_per_second":	126159024.57211637,
					"retransmits":	0,
					"snd_cwnd":	344624,
					"snd_wnd":	1818624,
					"rtt":	22255,
					"rttvar":	200,
					"pmtu":	9001,
					"omitted":	false,
					"sender":	true
				}],
			"sum":	{
				"start":	20.200808,
				"end":	20.400285,
				"seconds":	0.19947700202465057,
				"bytes":	3145728,
				"bits_per_second":	126159024.57211637,
				"retransmits":	0,
				"omitted":	false,
				"sender":	true
			}
		}, {
			"streams":	[{
					"socket":	5,
					"start":	20.400285,
					"end":	20.600093,
					"seconds":	0.19980800151824951,
					"bytes":	3407872,
					"bits_per_second":	136445866.99652231,
					"retransmits":	0,
					"snd_cwnd":	350416,
					"snd_wnd":	1818624,
					"rtt":	21613,
					"rttvar":	503,
					"pmtu":	9001,
					"omitted":	false,
					"sender":	true
				}],
			"sum":	{
				"start":	20.400285,
				"end":	20.600093,
				"seconds":	0.19980800151824951,
				"bytes":	3407872,
				"bits_per_second":	136445866.99652231,
				"retransmits":	0,
				"omitted":	false,
				"sender":	true
			}
		}, {
			"streams":	[{
					"socket":	5,
					"start":	20.600093,
					"end":	20.800254,
					"seconds":	0.20016099512577057,
					"bytes":	2883584,
					"bits_per_second":	115250586.08698897,
					"retransmits":	0,
					"snd_cwnd":	356208,
					"snd_wnd":	1755136,
					"rtt":	22154,
					"rttvar":	1092,
					"pmtu":	9001,
					"omitted":	false,
					"sender":	true
				}],
			"sum":	{
				"start":	20.600093,
				"end":	20.800254,
				"seconds":	0.20016099512577057,
				"bytes":	2883584,
				"bits_per_second":	115250586.08698897,
				"retransmits":	0,
				"omitted":	false,
				"sender":	true
			}
		}, {
			"streams":	[{
					"socket":	5,
					"start":	20.800254,
					"end":	21.002168,
					"seconds":	0.20191399753093719,
					"bytes":	4325376,
					"bits_per_second":	171374983.52335945,
					"retransmits":	0,
					"snd_cwnd":	363448,
					"snd_wnd":	1755136,
					"rtt":	21871,
					"rttvar":	451,
					"pmtu":	9001,
					"omitted":	false,
					"sender":	true
				}],
			"sum":	{
				"start":	20.800254,
				"end":	21.002168,
				"seconds":	0.20191399753093719,
				"bytes":	4325376,
				"bits_per_second":	171374983.52335945,
				"retransmits":	0,
				"omitted":	false,
				"sender":	true
			}
		}, {
			"streams":	[{
					"socket":	5,
					"start":	21.002168,
					"end":	21.200099,
					"seconds":	0.19793100655078888,
					"bytes":	2752512,
					"bits_per_second":	111251371.79732205,
					"retransmits":	0,
					"snd_cwnd":	370688,
					"snd_wnd":	1818624,
					"rtt":	22169,
					"rttvar":	1623,
					"pmtu":	9001,
					"omitted":	false,
					"sender":	true
				}],
			"sum":	{
				"start":	21.002168,
				"end":	21.200099,
				"seconds":	0.19793100655078888,
				"bytes":	2752512,
				"bits_per_second":	111251371.79732205,
				"retransmits":	0,
				"omitted":	false,
				"sender":	true
			}
		}, {
			"streams":	[{
					"socket":	5,
					"start":	21.200099,
					"end":	21.40026,
					"seconds":	0.20016099512577057,
					"bytes":	3014656,
					"bits_per_second":	120489249.090943,
					"retransmits":	14,
					"snd_cwnd":	264984,
					"snd_wnd":	1818624,
					"rtt":	21567,
					"rttvar":	541,
					"pmtu":	9001,
					"omitted":	false,
					"sender":	true
				}],
			"sum":	{
				"start":	21.200099,
				"end":	21.40026,
				"seconds":	0.20016099512577057,
				"bytes":	3014656,
				"bits_per_second":	120489249.090943,
				"retransmits":	14,
				"omitted":	false,
				"sender":	true
			}
		}, {
			"streams":	[{
					"socket":	5,
					"start":	21.40026,
					"end":	21.600731,
					"seconds":	0.20047099888324738,
					"bytes":	2883584,
					"bits_per_second":	115072365.222438,
					"retransmits":	0,
					"snd_cwnd":	276568,
					"snd_wnd":	1799936,
					"rtt":	21504,
					"rttvar":	362,
					"pmtu":	9001,
					"omitted":	false,
					"sender":	true
				}],
			"sum":	{
				"start":	21.40026,
				"end":	21.600731,
				"seconds":	0.20047099888324738,
				"bytes":	2883584,
				"bits_per_second":	115072365.222438,
				"retransmits":	0,
				"omitted":	false,
				"sender":	true
			}
		}, {
			"streams":	[{
					"socket":	5,
					"start":	21.600731,
					"end":	21.800296,
					"seconds":	0.19956499338150024,
					"bytes":	3145728,
					"bits_per_second":	126103399.06604522,
					"retransmits":	0,
					"snd_cwnd":	288152,
					"snd_wnd":	1818624,
					"rtt":	21640,
					"rttvar":	226,
					"pmtu":	9001,
					"omitted":	false,
					"sender":	true
				}],
			"sum":	{
				"start":	21.600731,
				"end":	21.800296,
				"seconds":	0.19956499338150024,
				"bytes":	3145728,
				"bits_per_second":	126103399.06604522,
				"retransmits":	0,
				"omitted":	false,
				"sender":	true
			}
		}, {
			"streams":	[{
					"socket":	5,
					"start":	21.800296,
					"end":	22.000261,
					"seconds":	0.19996500015258789,
					"bytes":	1441792,
					"bits_per_second":	57681774.266488932,
					"retransmits":	0,
					"snd_cwnd":	298288,
					"snd_wnd":	1818624,
					"rtt":	21816,
					"rttvar":	292,
					"pmtu":	9001,
					"omitted":	false,
					"sender":	true
				}],
			"sum":	{
				"start":	21.800296,
				"end":	22.000261,
				"seconds":	0.19996500015258789,
				"bytes":	1441792,
				"bits_per_second":	57681774.266488932,
				"retransmits":	0,
				"omitted":	false,
				"sender":	true
			}
		}, {
			"streams":	[{
					"socket":	5,
					"start":	22.000261,
					"end":	22.200274,
					"seconds":	0.20001299679279327,
					"bytes":	2883584,
					"bits_per_second":	115335865.01830362,
					"retransmits":	0,
					"snd_cwnd":	308424,
					"snd_wnd":	1818624,
					"rtt":	21479,
					"rttvar":	531,
					"pmtu":	9001,
					"omitted":	false,
					"sender":	true
				}],
			"sum":	{
				"start":	22.000261,
				"end":	22.200274,
				"seconds":	0.20001299679279327,
				"bytes":	2883584,
				"bits_per_second":	115335865.01830362,
				"retransmits":	0,
				"omitted":	false,
				"sender":	true
			}
		}, {
			"streams":	[{
					"socket":	5,
					"start":	22.200274,
					"end":	22.400283,
					"seconds":	0.20000900328159332,
					"bytes":	3145728,
					"bits_per_second":	125823455.87997834,
					"retransmits":	0,
					"snd_cwnd":	314216,
					"snd_wnd":	1681664,
					"rtt":	22167,
					"rttvar":	403,
					"pmtu":	9001,
					"omitted":	false,
					"sender":	true
				}],
			"sum":	{
				"start":	22.200274,
				"end":	22.400283,
				"seconds":	0.20000900328159332,
				"bytes":	3145728,
				"bits_per_second":	125823455.87997834,
				"retransmits":	0,
				"omitted":	false,
				"sender":	true
			}
		}, {
			"streams":	[{
					"socket":	5,
					"start":	22.400283,
					"end":	22.600927,
					"seconds":	0.20064400136470795,
					"bytes":	2883584,
					"bits_per_second":	114973145.68636607,
					"retransmits":	0,
					"snd_cwnd":	321456,
					"snd_wnd":	1805696,
					"rtt":	21628,
					"rttvar":	711,
					"pmtu":	9001,
					"omitted":	false,
					"sender":	true
				}],
			"sum":	{
				"start":	22.400283,
				"end":	22.600927,
				"seconds":	0.20064400136470795,
				"bytes":	2883584,
				"bits_per_second":	114973145.68636607,
				"retransmits":	0,
				"omitted":	false,
				"sender":	true
			}
		}, {
			"streams":	[{
					"socket":	5,
					"start":	22.600927,
					"end":	22.800121,
					"seconds":	0.199193999171257,
					"bytes":	3145728,
					"bits_per_second":	126338263.72632684,
					"retransmits":	0,
					"snd_cwnd":	328696,
					"snd_wnd":	1785472,
					"rtt":	21742,
					"rttvar":	253,
					"pmtu":	9001,
					"omitted":	false,
					"sender":	true
				}],
			"sum":	{
				"start":	22.600927,
				"end":	22.800121,
				"seconds":	0.199193999171257,
				"bytes":	3145728,
				"bits_per_second":	126338263.72632684,
				"retransmits":	0,
				"omitted":	false,
				"sender":	true
			}
		}, {
			"streams":	[{
					"socket":	5,
					"start":	22.800121,
					"end":	23.000252,
					"seconds":	0.20013099908828735,
					"bytes":	3407872,
					"bits_per_second":	136225652.81839719,
					"retransmits":	0,
					"snd_cwnd":	335936,
					"snd_wnd":	1818624,
					"rtt":	22307,
					"rttvar":	684,
					"pmtu":	9001,
					"omitted":	false,
					"sender":	true
				}],
			"sum":	{
				"start":	22.800121,
				"end":	23.000252,
				"seconds":	0.20013099908828735,
				"bytes":	3407872,
				"bits_per_second":	136225652.81839719,
				"retransmits":	0,
				"omitted":	false,
				"sender":	true
			}
		}, {
			"streams":	[{
					"socket":	5,
					"start":	23.000252,
					"end":	23.200293,
					"seconds":	0.20004099607467651,
					"bytes":	3014656,
					"bits_per_second":	120561527.25312808,
					"retransmits":	0,
					"snd_cwnd":	341728,
					"snd_wnd":	1789824,
					"rtt":	21623,
					"rttvar":	396,
					"pmtu":	9001,
					"omitted":	false,
					"sender":	true
				}],
			"sum":	{
				"start":	23.000252,
				"end":	23.200293,
				"seconds":	0.20004099607467651,
				"bytes":	3014656,
				"bits_per_second":	120561527.25312808,
				"retransmits":	0,
				"omitted":	false,
				"sender":	true
			}
		}, {
			"streams":	[{
					"socket":	5,
					"start":	23.200293,
					"end":	23.400558,
					"seconds":	0.20026500523090363,
					"bytes":	3145728,
					"bits_per_second":	125662613.75013596,
					"retransmits":	0,
					"snd_cwnd":	346072,
					"snd_wnd":	1772544,
					"rtt":	21503,
					"rttvar":	580,
					"pmtu":	9001,
					"omitted":	false,
					"sender":	true
				}],
			"sum":	{
				"start":	23.200293,
				"end":	23.400558,
				"seconds":	0.20026500523090363,
				"bytes":	3145728,
				"bits_per_second":	125662613.75013596,
				"retransmits":	0,
				"omitted":	false,
				"sender":	true
			}
		}, {
			"streams":	[{
					"socket":	5,
					"start":	23.400558,
					"end":	23.600268,
					"seconds":	0.19970999658107758,
					"bytes":	2752512,
					"bits_per_second":	110260359.40599677,
					"retransmits":	0,
					"snd_cwnd":	351864,
					"snd_wnd":	1765248,
					"rtt":	21633,
					"rttvar":	375,
					"pmtu":	9001,
					"omitted":	false,
					"sender":	true
				}],
			"sum":	{
				"start":	23.400558,
				"end":	23.600268,
				"seconds":	0.19970999658107758,
				"bytes":	2752512,
				"bits_per_second":	110260359.40599677,
				"retransmits":	0,
				"omitted":	false,
				"sender":	true
			}
		}, {
			"streams":	[{
					"socket":	5,
					"start":	23.600268,
					"end":	23.800263,
					"seconds":	0.19999499619007111,
					"bytes":	2752512,
					"bits_per_second":	110103234.67829444,
					"retransmits":	0,
					"snd_cwnd":	354760,
					"snd_wnd":	1808640,
					"rtt":	22004,
					"rttvar":	97,
					"pmtu":	9001,
					"omitted":	false,
					"sender":	true
				}],
			"sum":	{
				"start":	23.600268,
				"end":	23.800263,
				"seconds":	0.19999499619007111,
				"bytes":	2752512,
				"bits_per_second":	110103234.67829444,
				"retransmits":	0,
				"omitted":	false,
				"sender":	true
			}
		}, {
			"streams":	[{
					"socket":	5,
					"start":	23.800263,
					"end":	24.000265,
					"seconds":	0.20000199973583221,
					"bytes":	4325376,
					"bits_per_second":	173013310.09542176,
					"retransmits":	0,
					"snd_cwnd":	359104,
					"snd_wnd":	1786880,
					"rtt":	22518,
					"rttvar":	858,
					"pmtu":	9001,
					"omitted":	false,
					"sender":	true
				}],
			"sum":	{
				"start":	23.800263,
				"end":	24.000265,
				"seconds":	0.20000199973583221,
				"bytes":	4325376,
				"bits_per_second":	173013310.09542176,
				"retransmits":	0,
				"omitted":	false,
				"sender":	true
			}
		}, {
			"streams":	[{
					"socket":	5,
					"start":	24.000265,
					"end":	24.200673,
					"seconds":	0.20040799677371979,
					"bytes":	2883584,
					"bits_per_second":	115108540.43437591,
					"retransmits":	0,
					"snd_cwnd":	362000,
					"snd_wnd":	1661440,
					"rtt":	21986,
					"rttvar":	399,
					"pmtu":	9001,
					"omitted":	false,
					"sender":	true
				}],
			"sum":	{
				"start":	24.000265,
				"end":	24.200673,
				"seconds":	0.20040799677371979,
				"bytes":	2883584,
				"bits_per_second":	115108540.43437591,
				"retransmits":	0,
				"omitted":	false,
				"sender":	true
			}
		}, {
			"streams":	[{
					"socket":	5,
					"start":	24.200673,
					"end":	24.400102,
					"seconds":	0.19942900538444519,
					"bytes":	2883584,
					"bits_per_second":	115673605.02816448,
					"retransmits":	0,
					"snd_cwnd":	367792,
					"snd_wnd":	1818624,
					"rtt":	21621,
					"rttvar":	720,
					"pmtu":	9001,
					"omitted":	false,
					"sender":	true
				}],
			"sum":	{
				"start":	24.200673,
				"end":	24.400102,
				"seconds":	0.19942900538444519,
				"bytes":	2883584,
				"bits_per_second":	115673605.02816448,
				"retransmits":	0,
				"omitted":	false,
				"sender":	true
			}
		}, {
			"streams":	[{
					"socket":	5,
					"start":	24.400102,
					"end":	24.60027,
					"seconds":	0.20016799867153168,
					"bytes":	3014656,
					"bits_per_second":	120485033.37227005,
					"retransmits":	0,
					"snd_cwnd":	375032,
					"snd_wnd":	1786880,
					"rtt":	21810,
					"rttvar":	285,
					"pmtu":	9001,
					"omitted":	false,
					"sender":	true
				}],
			"sum":	{
				"start":	24.400102,
				"end":	24.60027,
				"seconds":	0.20016799867153168,
				"bytes":	3014656,
				"bits_per_second":	120485033.37227005,
				"retransmits":	0,
				"omitted":	false,
				"sender":	true
			}
		}, {
			"streams":	[{
					"socket":	5,
					"start":	24.60027,
					"end":	24.800351,
					"seconds":	0.200081005692482,
					"bytes":	4456448,
					"bits_per_second":	178185749.69977573,
					"retransmits":	0,
					"snd_cwnd":	382272,
					"snd_wnd":	1646976,
					"rtt":	21837,
					"rttvar":	339,
					"pmtu":	9001,
					"omitted":	false,
					"sender":	true
				}],
			"sum":	{
				"start":	24.60027,
				"end":	24.800351,
				"seconds":	0.200081005692482,
				"bytes":	4456448,
				"bits_per_second":	178185749.69977573,
				"retransmits":	0,
				"omitted":	false,
				"sender":	true
			}
		}, {
			"streams":	[{
					"socket":	5,
					"start":	24.800351,
					"end":	25.000263,
					"seconds":	0.19991199672222137,
					"bytes":	3014656,
					"bits_per_second":	120639323.27938791,
					"retransmits":	0,
					"snd_cwnd":	389512,
					"snd_wnd":	1818624,
					"rtt":	21667,
					"rttvar":	370,
					"pmtu":	9001,
					"omitted":	false,
					"sender":	true
				}],
			"sum":	{
				"start":	24.800351,
				"end":	25.000263,
				"seconds":	0.19991199672222137,
				"bytes":	3014656,
				"bits_per_second":	120639323.27938791,
				"retransmits":	0,
				"omitted":	false,
				"sender":	true
			}
		}, {
			"streams":	[{
					"socket":	5,
					"start":	25.000263,
					"end":	25.20028,
					"seconds":	0.20001700520515442,
					"bytes":	3014656,
					"bits_per_second":	120575987.90294507,
					"retransmits":	0,
					"snd_cwnd":	396752,
					"snd_wnd":	1818624,
					"rtt":	22079,
					"rttvar":	243,
					"pmtu":	9001,
					"omitted":	false,
					"sender":	true
				}],
			"sum":	{
				"start":	25.000263,
				"end":	25.20028,
				"seconds":	0.20001700520515442,
				"bytes":	3014656,
				"bits_per_second":	120575987.90294507,
				"retransmits":	0,
				"omitted":	false,
				"sender":	true
			}
		}, {
			"streams":	[{
					"socket":	5,
					"start":	25.20028,
					"end":	25.40027,
					"seconds":	0.19999000430107117,
					"bytes":	3276800,
					"bits_per_second":	131078551.10866454,
					"retransmits":	2,
					"snd_cwnd":	283808,
					"snd_wnd":	1675776,
					"rtt":	22065,
					"rttvar":	429,
					"pmtu":	9001,
					"omitted":	false,
					"sender":	true
				}],
			"sum":	{
				"start":	25.20028,
				"end":	25.40027,
				"seconds":	0.19999000430107117,
				"bytes":	3276800,
				"bits_per_second":	131078551.10866454,
				"retransmits":	2,
				"omitted":	false,
				"sender":	true
			}
		}, {
			"streams":	[{
					"socket":	5,
					"start":	25.40027,
					"end":	25.600268,
					"seconds":	0.19999800622463226,
					"bytes":	2752512,
					"bits_per_second":	110101577.58906673,
					"retransmits":	0,
					"snd_cwnd":	296840,
					"snd_wnd":	1818624,
					"rtt":	22013,
					"rttvar":	191,
					"pmtu":	9001,
					"omitted":	false,
					"sender":	true
				}],
			"sum":	{
				"start":	25.40027,
				"end":	25.600268,
				"seconds":	0.19999800622463226,
				"bytes":	2752512,
				"bits_per_second":	110101577.58906673,
				"retransmits":	0,
				"omitted":	false,
				"sender":	true
			}
		}, {
			"streams":	[{
					"socket":	5,
					"start":	25.600268,
					"end":	25.800273,
					"seconds":	0.20000499486923218,
					"bytes":	3014656,
					"bits_per_second":	120583228.51270993,
					"retransmits":	0,
					"snd_cwnd":	306976,
					"snd_wnd":	1590656,
					"rtt":	22301,
					"rttvar":	232,
					"pmtu":	9001,
					"omitted":	false,
					"sender":	true
				}],
			"sum":	{
				"start":	25.600268,
				"end":	25.800273,
				"seconds":	0.20000499486923218,
				"bytes":	3014656,
				"bits_per_second":	120583228.51270993,
				"retransmits":	0,
				"omitted":	false,
				"sender":	true
			}
		}, {
			"streams":	[{
					"socket":	5,
					"start":	25.800273,
					"end":	26.000932,
					"seconds":	0.20065900683403015,
					"bytes":	1572864,
					"bits_per_second":	62707935.210741,
					"retransmits":	0,
					"snd_cwnd":	315664,
					"snd_wnd":	1804288,
					"rtt":	21671,
					"rttvar":	525,
					"pmtu":	9001,
					"omitted":	false,
					"sender":	true
				}],
			"sum":	{
				"start":	25.800273,
				"end":	26.000932,
				"seconds":	0.20065900683403015,
				"bytes":	1572864,
				"bits_per_second":	62707935.210741,
				"retransmits":	0,
				"omitted":	false,
				"sender":	true
			}
		}, {
			"streams":	[{
					"socket":	5,
					"start":	26.000932,
					"end":	26.201217,
					"seconds":	0.20028500258922577,
					"bytes":	3145728,
					"bits_per_second":	125650067.02780342,
					"retransmits":	0,
					"snd_cwnd":	325800,
					"snd_wnd":	1818624,
					"rtt":	22556,
					"rttvar":	280,
					"pmtu":	9001,
					"omitted":	false,
					"sender":	true
				}],
			"sum":	{
				"start":	26.000932,
				"end":	26.201217,
				"seconds":	0.20028500258922577,
				"bytes":	3145728,
				"bits_per_second":	125650067.02780342,
				"retransmits":	0,
				"omitted":	false,
				"sender":	true
			}
		}, {
			"streams":	[{
					"socket":	5,
					"start":	26.201217,
					"end":	26.400101,
					"seconds":	0.19888399541378021,
					"bytes":	3276800,
					"bits_per_second":	131807488.81005065,
					"retransmits":	0,
					"snd_cwnd":	334488,
					"snd_wnd":	1811456,
					"rtt":	21990,
					"rttvar":	167,
					"pmtu":	9001,
					"omitted":	false,
					"sender":	true
				}],
			"sum":	{
				"start":	26.201217,
				"end":	26.400101,
				"seconds":	0.19888399541378021,
				"bytes":	3276800,
				"bits_per_second":	131807488.81005065,
				"retransmits":	0,
				"omitted":	false,
				"sender":	true
			}
		}, {
			"streams":	[{
					"socket":	5,
					"start":	26.400101,
					"end":	26.600482,
					"seconds":	0.20038099586963654,
					"bytes":	3407872,
					"bits_per_second":	136055696.70756948,
					"retransmits":	0,
					"snd_cwnd":	341728,
					"snd_wnd":	1818624,
					"rtt":	21995,
					"rttvar":	40,
					"pmtu":	9001,
					"omitted":	false,
					"sender":	true
				}],
			"sum":	{
				"start":	26.400101,
				"end":	26.600482,
				"seconds":	0.20038099586963654,
				"bytes":	3407872,
				"bits_per_second":	136055696.70756948,
				"retransmits":	0,
				"omitted":	false,
				"sender":	true
			}
		}, {
			"streams":	[{
					"socket":	5,
					"start":	26.600482,
					"end":	26.800265,
					"seconds":	0.19978299736976624,
					"bytes":	3407872,
					"bits_per_second":	136462944.08898377,
					"retransmits":	0,
					"snd_cwnd":	347520,
					"snd_wnd":	1818624,
					"rtt":	21946,
					"rttvar":	51,
					"pmtu":	9001,
					"omitted":	false,
					"sender":	true
				}],
			"sum":	{
				"start":	26.600482,
				"end":	26.800265,
				"seconds":	0.19978299736976624,
				"bytes":	3407872,
				"bits_per_second":	136462944.08898377,
				"retransmits":	0,
				"omitted":	false,
				"sender":	true
			}
		}, {
			"streams":	[{
					"socket":	5,
					"start":	26.800265,
					"end":	27.000269,
					"seconds":	0.20000399649143219,
					"bytes":	3145728,
					"bits_per_second":	125826605.67524238,
					"retransmits":	0,
					"snd_cwnd":	353312,
					"snd_wnd":	1818624,
					"rtt":	22185,
					"rttvar":	428,
					"pmtu":	9001,
					"omitted":	false,
					"sender":	true
				}],
			"sum":	{
				"start":	26.800265,
				"end":	27.000269,
				"seconds":	0.20000399649143219,
				"bytes":	3145728,
				"bits_per_second":	125826605.67524238,
				"retransmits":	0,
				"omitted":	false,
				"sender":	true
			}
		}, {
			"streams":	[{
					"socket":	5,
					"start":	27.000269,
					"end":	27.200259,
					"seconds":	0.19999000430107117,
					"bytes":	2752512,
					"bits_per_second":	110105982.93127823,
					"retransmits":	0,
					"snd_cwnd":	360552,
					"snd_wnd":	1818624,
					"rtt":	22531,
					"rttvar":	1533,
					"pmtu":	9001,
					"omitted":	false,
					"sender":	true
				}],
			"sum":	{
				"start":	27.000269,
				"end":	27.200259,
				"seconds":	0.19999000430107117,
				"bytes":	2752512,
				"bits_per_second":	110105982.93127823,
				"retransmits":	0,
				"omitted":	false,
				"sender":	true
			}
		}, {
			"streams":	[{
					"socket":	5,
					"start":	27.200259,
					"end":	27.400251,
					"seconds":	0.19999200105667114,
					"bytes":	2883584,
					"bits_per_second":	115347973.309508,
					"retransmits":	0,
					"snd_cwnd":	364896,
					"snd_wnd":	1818624,
					"rtt":	21634,
					"rttvar":	293,
					"pmtu":	9001,
					"omitted":	false,
					"sender":	true
				}],
			"sum":	{
				"start":	27.200259,
				"end":	27.400251,
				"seconds":	0.19999200105667114,
				"bytes":	2883584,
				"bits_per_second":	115347973.309508,
				"retransmits":	0,
				"omitted":	false,
				"sender":	true
			}
		}, {
			"streams":	[{
					"socket":	5,
					"start":	27.400251,
					"end":	27.600276,
					"seconds":	0.20002500712871552,
					"bytes":	4456448,
					"bits_per_second":	178235634.19277024,
					"retransmits":	0,
					"snd_cwnd":	370688,
					"snd_wnd":	1749376,
					"rtt":	21876,
					"rttvar":	231,
					"pmtu":	9001,
					"omitted":	false,
					"sender":	true
				}],
			"sum":	{
				"start":	27.400251,
				"end":	27.600276,
				"seconds":	0.20002500712871552,
				"bytes":	4456448,
				"bits_per_second":	178235634.19277024,
				"retransmits":	0,
				"omitted":	false,
				"sender":	true
			}
		}, {
			"streams":	[{
					"socket":	5,
					"start":	27.600276,
					"end":	27.800499,
					"seconds":	0.20022299885749817,
					"bytes":	2883584,
					"bits_per_second":	115214896.04907143,
					"retransmits":	0,
					"snd_cwnd":	373584,
					"snd_wnd":	1808640,
					"rtt":	22314,
					"rttvar":	731,
					"pmtu":	9001,
					"omitted":	false,
					"sender":	true
				}],
			"sum":	{
				"start":	27.600276,
				"end":	27.800499,
				"seconds":	0.20022299885749817,
				"bytes":	2883584,
				"bits_per_second":	115214896.04907143,
				"retransmits":	0,
				"omitted":	false,
				"sender":	true
			}
		}, {
			"streams":	[{
					"socket":	5,
					"start":	27.800499,
					"end":	28.001766,
					"seconds":	0.20126700401306152,
					"bytes":	2883584,
					"bits_per_second":	114617257.37470074,
					"retransmits":	0,
					"snd_cwnd":	377928,
					"snd_wnd":	1798528,
					"rtt":	21369,
					"rttvar":	325,
					"pmtu":	9001,
					"omitted":	false,
					"sender":	true
				}],
			"sum":	{
				"start":	27.800499,
				"end":	28.001766,
				"seconds":	0.20126700401306152,
				"bytes":	2883584,
				"bits_per_second":	114617257.37470074,
				"retransmits":	0,
				"omitted":	false,
				"sender":	true
			}
		}, {
			"streams":	[{
					"socket":	5,
					"start":	28.001766,
					"end":	28.200257,
					"seconds":	0.19849100708961487,
					"bytes":	4456448,
					"bits_per_second":	179613094.43054011,
					"retransmits":	0,
					"snd_cwnd":	380824,
					"snd_wnd":	1818624,
					"rtt":	21437,
					"rttvar":	543,
					"pmtu":	9001,
					"omitted":	false,
					"sender":	true
				}],
			"sum":	{
				"start":	28.001766,
				"end":	28.200257,
				"seconds":	0.19849100708961487,
				"bytes":	4456448,
				"bits_per_second":	179613094.43054011,
				"retransmits":	0,
				"omitted":	false,
				"sender":	true
			}
		}, {
			"streams":	[{
					"socket":	5,
					"start":	28.200257,
					"end":	28.40025,
					"seconds":	0.19999299943447113,
					"bytes":	3014656,
					"bits_per_second":	120590461.00712219,
					"retransmits":	0,
					"snd_cwnd":	385168,
					"snd_wnd":	1818624,
					"rtt":	21407,
					"rttvar":	466,
					"pmtu":	9001,
					"omitted":	false,
					"sender":	true
				}],
			"sum":	{
				"start":	28.200257,
				"end":	28.40025,
				"seconds":	0.19999299943447113,
				"bytes":	3014656,
				"bits_per_second":	120590461.00712219,
				"retransmits":	0,
				"omitted":	false,
				"sender":	true
			}
		}, {
			"streams":	[{
					"socket":	5,
					"start":	28.40025,
					"end":	28.600271,
					"seconds":	0.20002099871635437,
					"bytes":	3014656,
					"bits_per_second":	120573580.54791121,
					"retransmits":	0,
					"snd_cwnd":	390960,
					"snd_wnd":	1677312,
					"rtt":	21620,
					"rttvar":	344,
					"pmtu":	9001,
					"omitted":	false,
					"sender":	true
				}],
			"sum":	{
				"start":	28.40025,
				"end":	28.600271,
				"seconds":	0.20002099871635437,
				"bytes":	3014656,
				"bits_per_second":	120573580.54791121,
				"retransmits":	0,
				"omitted":	false,
				"sender":	true
			}
		}, {
			"streams":	[{
					"socket":	5,
					"start":	28.600271,
					"end":	28.800577,
					"seconds":	0.2003059983253479,
					"bytes":	3145728,
					"bits_per_second":	125636896.60019217,
					"retransmits":	0,
					"snd_cwnd":	398200,
					"snd_wnd":	1818624,
					"rtt":	21671,
					"rttvar":	306,
					"pmtu":	9001,
					"omitted":	false,
					"sender":	true
				}],
			"sum":	{
				"start":	28.600271,
				"end":	28.800577,
				"seconds":	0.2003059983253479,
				"bytes":	3145728,
				"bits_per_second":	125636896.60019217,
				"retransmits":	0,
				"omitted":	false,
				"sender":	true
			}
		}, {
			"streams":	[{
					"socket":	5,
					"start":	28.800577,
					"end":	29.00028,
					"seconds":	0.19970299303531647,
					"bytes":	4587520,
					"bits_per_second":	183773710.35951254,
					"retransmits":	0,
					"snd_cwnd":	405440,
					"snd_wnd":	1727744,
					"rtt":	21579,
					"rttvar":	267,
					"pmtu":	9001,
					"omitted":	false,
					"sender":	true
				}],
			"sum":	{
				"start":	28.800577,
				"end":	29.00028,
				"seconds":	0.19970299303531647,
				"bytes":	4587520,
				"bits_per_second":	183773710.35951254,
				"retransmits":	0,
				"omitted":	false,
				"sender":	true
			}
		}, {
			"streams":	[{
					"socket":	5,
					"start":	29.00028,
					"end":	29.200262,
					"seconds":	0.19998200237751007,
					"bytes":	2883584,
					"bits_per_second":	115353740.46536848,
					"retransmits":	0,
					"snd_cwnd":	412680,
					"snd_wnd":	1818624,
					"rtt":	21737,
					"rttvar":	228,
					"pmtu":	9001,
					"omitted":	false,
					"sender":	true
				}],
			"sum":	{
				"start":	29.00028,
				"end":	29.200262,
				"seconds":	0.19998200237751007,
				"bytes":	2883584,
				"bits_per_second":	115353740.46536848,
				"retransmits":	0,
				"omitted":	false,
				"sender":	true
			}
		}, {
			"streams":	[{
					"socket":	5,
					"start":	29.200262,
					"end":	29.400279,
					"seconds":	0.20001700520515442,
					"bytes":	4980736,
					"bits_per_second":	199212501.75269186,
					"retransmits":	0,
					"snd_cwnd":	421368,
					"snd_wnd":	1818624,
					"rtt":	21462,
					"rttvar":	433,
					"pmtu":	9001,
					"omitted":	false,
					"sender":	true
				}],
			"sum":	{
				"start":	29.200262,
				"end":	29.400279,
				"seconds":	0.20001700520515442,
				"bytes":	4980736,
				"bits_per_second":	199212501.75269186,
				"retransmits":	0,
				"omitted":	false,
				"sender":	true
			}
		}, {
			"streams":	[{
					"socket":	5,
					"start":	29.400279,
					"end":	29.600103,
					"seconds":	0.1998240053653717,
					"bytes":	1703936,
					"bits_per_second":	68217469.54313755,
					"retransmits":	15,
					"snd_cwnd":	302632,
					"snd_wnd":	1818624,
					"rtt":	21549,
					"rttvar":	187,
					"pmtu":	9001,
					"omitted":	false,
					"sender":	true
				}],
			"sum":	{
				"start":	29.400279,
				"end":	29.600103,
				"seconds":	0.1998240053653717,
				"bytes":	1703936,
				"bits_per_second":	68217469.54313755,
				"retransmits":	15,
				"omitted":	false,
				"sender":	true
			}
		}, {
			"streams":	[{
					"socket":	5,
					"start":	29.600103,
					"end":	29.800337,
					"seconds":	0.20023399591445923,
					"bytes":	3014656,
					"bits_per_second":	120445321.43434317,
					"retransmits":	0,
					"snd_cwnd":	317112,
					"snd_wnd":	1818624,
					"rtt":	21891,
					"rttvar":	92,
					"pmtu":	9001,
					"omitted":	false,
					"sender":	true
				}],
			"sum":	{
				"start":	29.600103,
				"end":	29.800337,
				"seconds":	0.20023399591445923,
				"bytes":	3014656,
				"bits_per_second":	120445321.43434317,
				"retransmits":	0,
				"omitted":	false,
				"sender":	true
			}
		}, {
			"streams":	[{
					"socket":	5,
					"start":	29.800337,
					"end":	30.000551,
					"seconds":	0.20021399855613708,
					"bytes":	3145728,
					"bits_per_second":	125694627.65583731,
					"retransmits":	0,
					"snd_cwnd":	327248,
					"snd_wnd":	1818624,
					"rtt":	21899,
					"rttvar":	104,
					"pmtu":	9001,
					"omitted":	false,
					"sender":	true
				}],
			"sum":	{
				"start":	29.800337,
				"end":	30.000551,
				"seconds":	0.20021399855613708,
				"bytes":	3145728,
				"bits_per_second":	125694627.65583731,
				"retransmits":	0,
				"omitted":	false,
				"sender":	true
			}
		}],
	"end":	{
		"streams":	[{
				"sender":	{
					"socket":	5,
					"start":	0,
					"end":	30.000551,
					"seconds":	30.000551,
					"bytes":	457310208,
					"bits_per_second":	121947149.03736268,
					"retransmits":	438,
					"max_snd_cwnd":	525624,
					"max_snd_wnd":	1818624,
					"max_rtt":	23481,
					"min_rtt":	20718,
					"mean_rtt":	21799,
					"sender":	true
				},
				"receiver":	{
					"socket":	5,
					"start":	0,
					"end":	30.021011,
					"seconds":	30.000551,
					"bytes":	454557696,
					"bits_per_second":	121130549.80060464,
					"sender":	true
				}
			}],
		"sum_sent":	{
			"start":	0,
			"end":	30.000551,
			"seconds":	30.000551,
			"bytes":	457310208,
			"bits_per_second":	121947149.03736268,
			"retransmits":	438,
			"sender":	true
		},
		"sum_received":	{
			"start":	0,
			"end":	30.021011,
			"seconds":	30.021011,
			"bytes":	454557696,
			"bits_per_second":	121130549.80060464,
			"sender":	true
		},
		"cpu_utilization_percent":	{
			"host_total":	0.33479367907406543,
			"host_user":	0.0455621223100498,
			"host_system":	0.28922823276005344,
			"remote_total":	3.5659094654192,
			"remote_user":	0.1048897811224842,
			"remote_system":	3.4610196842967151
		},
		"sender_tcp_congestion":	"cubic",
		"receiver_tcp_congestion":	"cubic"
	}
}
